[{"tl2_id": "NL11", "tl2_name_en": "Groningen", "children": [{"id": "NLDGM0014", "text": "Groningen", "tl2_name_en": "Groningen", "tl3_name_en": "Overig Groningen", "fuaname_en": "Groningen", "cityname_en": "Groningen"}, {"id": "NLDGM0037", "text": "Stadskanaal", "tl2_name_en": "Groningen", "tl3_name_en": "Oost-Groningen", "fuaname_en": "", "cityname_en": ""}, {"id": "NLDGM0047", "text": "Veendam", "tl2_name_en": "Groningen", "tl3_name_en": "Oost-Groningen", "fuaname_en": "Groningen", "cityname_en": ""}, {"id": "NLDGM0765", "text": "Pekela", "tl2_name_en": "Groningen", "tl3_name_en": "Oost-Groningen", "fuaname_en": "", "cityname_en": ""}, {"id": "NLDGM1895", "text": "Oldambt", "tl2_name_en": "Groningen", "tl3_name_en": "Oost-Groningen", "fuaname_en": "", "cityname_en": ""}, {"id": "NLDGM1950", "text": "Westerwolde", "tl2_name_en": "Groningen", "tl3_name_en": "Oost-Groningen", "fuaname_en": "", "cityname_en": ""}, {"id": "NLDGM1952", "text": "Midden-Groningen", "tl2_name_en": "Groningen", "tl3_name_en": "Overig Groningen", "fuaname_en": "Groningen", "cityname_en": ""}, {"id": "NLDGM1966", "text": "Het Hogeland", "tl2_name_en": "Groningen", "tl3_name_en": "Overig Groningen", "fuaname_en": "Groningen", "cityname_en": ""}, {"id": "NLDGM1969", "text": "Westerkwartier", "tl2_name_en": "Groningen", "tl3_name_en": "Overig Groningen", "fuaname_en": "Groningen", "cityname_en": ""}, {"id": "NLDGM1979", "text": "Eemsdelta", "tl2_name_en": "Groningen", "tl3_name_en": "Delfzijl en omgeving", "fuaname_en": "Groningen", "cityname_en": ""}]}, {"tl2_id": "NL23", "tl2_name_en": "Flevoland", "children": [{"id": "NLDGM0034", "text": "Almere", "tl2_name_en": "Flevoland", "tl3_name_en": "Flevoland", "fuaname_en": "Amsterdam", "cityname_en": "Almere"}, {"id": "NLDGM0050", "text": "Zeewolde", "tl2_name_en": "Flevoland", "tl3_name_en": "Flevoland", "fuaname_en": "", "cityname_en": ""}, {"id": "NLDGM0171", "text": "Noordoostpolder", "tl2_name_en": "Flevoland", "tl3_name_en": "Flevoland", "fuaname_en": "", "cityname_en": ""}, {"id": "NLDGM0184", "text": "Urk", "tl2_name_en": "Flevoland", "tl3_name_en": "Flevoland", "fuaname_en": "", "cityname_en": ""}, {"id": "NLDGM0303", "text": "Dronten", "tl2_name_en": "Flevoland", "tl3_name_en": "Flevoland", "fuaname_en": "Lelystad", "cityname_en": ""}, {"id": "NLDGM0995", "text": "Lelystad", "tl2_name_en": "Flevoland", "tl3_name_en": "Flevoland", "fuaname_en": "Lelystad", "cityname_en": "Lelystad"}]}, {"tl2_id": "NL12", "tl2_name_en": "Friesland", "children": [{"id": "NLDGM0059", "text": "Achtkarspelen", "tl2_name_en": "Friesland", "tl3_name_en": "Noord-Friesland", "fuaname_en": "", "cityname_en": ""}, {"id": "NLDGM0060", "text": "Ameland", "tl2_name_en": "Friesland", "tl3_name_en": "Noord-Friesland", "fuaname_en": "", "cityname_en": ""}, {"id": "NLDGM0072", "text": "Harlingen", "tl2_name_en": "Friesland", "tl3_name_en": "Noord-Friesland", "fuaname_en": "Leeuwarden", "cityname_en": ""}, {"id": "NLDGM0074", "text": "Heerenveen", "tl2_name_en": "Friesland", "tl3_name_en": "Zuidoost-Friesland", "fuaname_en": "", "cityname_en": ""}, {"id": "NLDGM0080", "text": "Leeuwarden", "tl2_name_en": "Friesland", "tl3_name_en": "Noord-Friesland", "fuaname_en": "Leeuwarden", "cityname_en": "Leeuwarden"}, {"id": "NLDGM0085", "text": "Ooststellingwerf", "tl2_name_en": "Friesland", "tl3_name_en": "Zuidoost-Friesland", "fuaname_en": "", "cityname_en": ""}, {"id": "NLDGM0086", "text": "Opsterland", "tl2_name_en": "Friesland", "tl3_name_en": "Zuidoost-Friesland", "fuaname_en": "", "cityname_en": ""}, {"id": "NLDGM0088", "text": "Schiermonnikoog", "tl2_name_en": "Friesland", "tl3_name_en": "Noord-Friesland", "fuaname_en": "", "cityname_en": ""}, {"id": "NLDGM0090", "text": "Smallingerland", "tl2_name_en": "Friesland", "tl3_name_en": "Zuidoost-Friesland", "fuaname_en": "", "cityname_en": ""}, {"id": "NLDGM0093", "text": "Terschelling", "tl2_name_en": "Friesland", "tl3_name_en": "Noord-Friesland", "fuaname_en": "", "cityname_en": ""}, {"id": "NLDGM0096", "text": "Vlieland", "tl2_name_en": "Friesland", "tl3_name_en": "Noord-Friesland", "fuaname_en": "", "cityname_en": ""}, {"id": "NLDGM0098", "text": "Weststellingwerf", "tl2_name_en": "Friesland", "tl3_name_en": "Zuidoost-Friesland", "fuaname_en": "", "cityname_en": ""}, {"id": "NLDGM0737", "text": "Tytsjerksteradiel", "tl2_name_en": "Friesland", "tl3_name_en": "Noord-Friesland", "fuaname_en": "Leeuwarden", "cityname_en": ""}, {"id": "NLDGM1891", "text": "Dantumadiel", "tl2_name_en": "Friesland", "tl3_name_en": "Noord-Friesland", "fuaname_en": "Leeuwarden", "cityname_en": ""}, {"id": "NLDGM1900", "text": "S\u00fadwest-Frysl\u00e2n", "tl2_name_en": "Friesland", "tl3_name_en": "Zuidwest-Friesland", "fuaname_en": "", "cityname_en": ""}, {"id": "NLDGM1940", "text": "De Fryske Marren", "tl2_name_en": "Friesland", "tl3_name_en": "Zuidwest-Friesland", "fuaname_en": "", "cityname_en": ""}, {"id": "NLDGM1949", "text": "Waadhoeke", "tl2_name_en": "Friesland", "tl3_name_en": "Noord-Friesland", "fuaname_en": "Leeuwarden", "cityname_en": ""}, {"id": "NLDGM1970", "text": "Noardeast-Frysl\u00e2n", "tl2_name_en": "Friesland", "tl3_name_en": "Noord-Friesland", "fuaname_en": "", "cityname_en": ""}]}, {"tl2_id": "NL13", "tl2_name_en": "Drenthe", "children": [{"id": "NLDGM0106", "text": "Assen", "tl2_name_en": "Drenthe", "tl3_name_en": "Noord-Drenthe", "fuaname_en": "Assen", "cityname_en": "Assen"}, {"id": "NLDGM0109", "text": "Coevorden", "tl2_name_en": "Drenthe", "tl3_name_en": "Zuidoost-Drenthe", "fuaname_en": "", "cityname_en": ""}, {"id": "NLDGM0114", "text": "Emmen", "tl2_name_en": "Drenthe", "tl3_name_en": "Zuidoost-Drenthe", "fuaname_en": "", "cityname_en": ""}, {"id": "NLDGM0118", "text": "Hoogeveen", "tl2_name_en": "Drenthe", "tl3_name_en": "Zuidwest-Drenthe", "fuaname_en": "", "cityname_en": ""}, {"id": "NLDGM0119", "text": "Meppel", "tl2_name_en": "Drenthe", "tl3_name_en": "Zuidwest-Drenthe", "fuaname_en": "", "cityname_en": ""}, {"id": "NLDGM1680", "text": "Aa en Hunze", "tl2_name_en": "Drenthe", "tl3_name_en": "Noord-Drenthe", "fuaname_en": "Assen", "cityname_en": ""}, {"id": "NLDGM1681", "text": "Borger-Odoorn", "tl2_name_en": "Drenthe", "tl3_name_en": "Zuidoost-Drenthe", "fuaname_en": "", "cityname_en": ""}, {"id": "NLDGM1690", "text": "De Wolden", "tl2_name_en": "Drenthe", "tl3_name_en": "Zuidwest-Drenthe", "fuaname_en": "", "cityname_en": ""}, {"id": "NLDGM1699", "text": "Noordenveld", "tl2_name_en": "Drenthe", "tl3_name_en": "Noord-Drenthe", "fuaname_en": "Groningen", "cityname_en": ""}, {"id": "NLDGM1701", "text": "Westerveld", "tl2_name_en": "Drenthe", "tl3_name_en": "Zuidwest-Drenthe", "fuaname_en": "", "cityname_en": ""}, {"id": "NLDGM1730", "text": "Tynaarlo", "tl2_name_en": "Drenthe", "tl3_name_en": "Noord-Drenthe", "fuaname_en": "Groningen", "cityname_en": ""}, {"id": "NLDGM1731", "text": "Midden-Drenthe", "tl2_name_en": "Drenthe", "tl3_name_en": "Noord-Drenthe", "fuaname_en": "Assen", "cityname_en": ""}]}, {"tl2_id": "NL21", "tl2_name_en": "Overijssel", "children": [{"id": "NLDGM0141", "text": "Almelo", "tl2_name_en": "Overijssel", "tl3_name_en": "Twente", "fuaname_en": "Almelo", "cityname_en": "Almelo"}, {"id": "NLDGM0147", "text": "Borne", "tl2_name_en": "Overijssel", "tl3_name_en": "Twente", "fuaname_en": "Enschede", "cityname_en": ""}, {"id": "NLDGM0148", "text": "Dalfsen", "tl2_name_en": "Overijssel", "tl3_name_en": "Noord-Overijssel", "fuaname_en": "Zwolle", "cityname_en": ""}, {"id": "NLDGM0150", "text": "Deventer", "tl2_name_en": "Overijssel", "tl3_name_en": "Zuidwest-Overijssel", "fuaname_en": "Deventer", "cityname_en": "Deventer"}, {"id": "NLDGM0153", "text": "Enschede", "tl2_name_en": "Overijssel", "tl3_name_en": "Twente", "fuaname_en": "Enschede", "cityname_en": "Enschede"}, {"id": "NLDGM0158", "text": "Haaksbergen", "tl2_name_en": "Overijssel", "tl3_name_en": "Twente", "fuaname_en": "Enschede", "cityname_en": ""}, {"id": "NLDGM0160", "text": "Hardenberg", "tl2_name_en": "Overijssel", "tl3_name_en": "Noord-Overijssel", "fuaname_en": "", "cityname_en": ""}, {"id": "NLDGM0163", "text": "Hellendoorn", "tl2_name_en": "Overijssel", "tl3_name_en": "Twente", "fuaname_en": "", "cityname_en": ""}, {"id": "NLDGM0164", "text": "Hengelo", "tl2_name_en": "Overijssel", "tl3_name_en": "Twente", "fuaname_en": "Enschede", "cityname_en": "Hengelo"}, {"id": "NLDGM0166", "text": "Kampen", "tl2_name_en": "Overijssel", "tl3_name_en": "Noord-Overijssel", "fuaname_en": "Zwolle", "cityname_en": ""}, {"id": "NLDGM0168", "text": "Losser", "tl2_name_en": "Overijssel", "tl3_name_en": "Twente", "fuaname_en": "Enschede", "cityname_en": ""}, {"id": "NLDGM0173", "text": "Oldenzaal", "tl2_name_en": "Overijssel", "tl3_name_en": "Twente", "fuaname_en": "Enschede", "cityname_en": ""}, {"id": "NLDGM0175", "text": "Ommen", "tl2_name_en": "Overijssel", "tl3_name_en": "Noord-Overijssel", "fuaname_en": "Zwolle", "cityname_en": ""}, {"id": "NLDGM0177", "text": "Raalte", "tl2_name_en": "Overijssel", "tl3_name_en": "Zuidwest-Overijssel", "fuaname_en": "Zwolle", "cityname_en": ""}, {"id": "NLDGM0180", "text": "Staphorst", "tl2_name_en": "Overijssel", "tl3_name_en": "Noord-Overijssel", "fuaname_en": "Zwolle", "cityname_en": ""}, {"id": "NLDGM0183", "text": "Tubbergen", "tl2_name_en": "Overijssel", "tl3_name_en": "Twente", "fuaname_en": "Almelo", "cityname_en": ""}, {"id": "NLDGM0189", "text": "Wierden", "tl2_name_en": "Overijssel", "tl3_name_en": "Twente", "fuaname_en": "Almelo", "cityname_en": ""}, {"id": "NLDGM0193", "text": "Zwolle", "tl2_name_en": "Overijssel", "tl3_name_en": "Noord-Overijssel", "fuaname_en": "Zwolle", "cityname_en": "Zwolle"}, {"id": "NLDGM1700", "text": "Twenterand", "tl2_name_en": "Overijssel", "tl3_name_en": "Twente", "fuaname_en": "Almelo", "cityname_en": ""}, {"id": "NLDGM1708", "text": "Steenwijkerland", "tl2_name_en": "Overijssel", "tl3_name_en": "Noord-Overijssel", "fuaname_en": "", "cityname_en": ""}, {"id": "NLDGM1735", "text": "Hof van Twente", "tl2_name_en": "Overijssel", "tl3_name_en": "Twente", "fuaname_en": "Enschede", "cityname_en": ""}, {"id": "NLDGM1742", "text": "Rijssen-Holten", "tl2_name_en": "Overijssel", "tl3_name_en": "Twente", "fuaname_en": "", "cityname_en": ""}, {"id": "NLDGM1773", "text": "Olst-Wijhe", "tl2_name_en": "Overijssel", "tl3_name_en": "Zuidwest-Overijssel", "fuaname_en": "Deventer", "cityname_en": ""}, {"id": "NLDGM1774", "text": "Dinkelland", "tl2_name_en": "Overijssel", "tl3_name_en": "Twente", "fuaname_en": "Enschede", "cityname_en": ""}, {"id": "NLDGM1896", "text": "Zwartewaterland", "tl2_name_en": "Overijssel", "tl3_name_en": "Noord-Overijssel", "fuaname_en": "Zwolle", "cityname_en": ""}]}, {"tl2_id": "NL22", "tl2_name_en": "Gelderland", "children": [{"id": "NLDGM0197", "text": "Aalten", "tl2_name_en": "Gelderland", "tl3_name_en": "Achterhoek", "fuaname_en": "", "cityname_en": ""}, {"id": "NLDGM0200", "text": "Apeldoorn", "tl2_name_en": "Gelderland", "tl3_name_en": "Veluwe", "fuaname_en": "Apeldoorn", "cityname_en": "Apeldoorn"}, {"id": "NLDGM0202", "text": "Arnhem", "tl2_name_en": "Gelderland", "tl3_name_en": "Arnhem/Nijmegen", "fuaname_en": "Arnhem", "cityname_en": "Arnhem"}, {"id": "NLDGM0203", "text": "Barneveld", "tl2_name_en": "Gelderland", "tl3_name_en": "Veluwe", "fuaname_en": "", "cityname_en": ""}, {"id": "NLDGM0209", "text": "Beuningen", "tl2_name_en": "Gelderland", "tl3_name_en": "Arnhem/Nijmegen", "fuaname_en": "Nijmegen", "cityname_en": ""}, {"id": "NLDGM0213", "text": "Brummen", "tl2_name_en": "Gelderland", "tl3_name_en": "Achterhoek", "fuaname_en": "Apeldoorn", "cityname_en": ""}, {"id": "NLDGM0214", "text": "Buren", "tl2_name_en": "Gelderland", "tl3_name_en": "Zuidwest-Gelderland", "fuaname_en": "", "cityname_en": ""}, {"id": "NLDGM0216", "text": "Culemborg", "tl2_name_en": "Gelderland", "tl3_name_en": "Zuidwest-Gelderland", "fuaname_en": "Utrecht", "cityname_en": ""}, {"id": "NLDGM0221", "text": "Doesburg", "tl2_name_en": "Gelderland", "tl3_name_en": "Arnhem/Nijmegen", "fuaname_en": "Arnhem", "cityname_en": ""}, {"id": "NLDGM0222", "text": "Doetinchem", "tl2_name_en": "Gelderland", "tl3_name_en": "Achterhoek", "fuaname_en": "", "cityname_en": ""}, {"id": "NLDGM0225", "text": "Druten", "tl2_name_en": "Gelderland", "tl3_name_en": "Arnhem/Nijmegen", "fuaname_en": "Nijmegen", "cityname_en": ""}, {"id": "NLDGM0226", "text": "Duiven", "tl2_name_en": "Gelderland", "tl3_name_en": "Arnhem/Nijmegen", "fuaname_en": "Arnhem", "cityname_en": ""}, {"id": "NLDGM0228", "text": "Ede", "tl2_name_en": "Gelderland", "tl3_name_en": "Veluwe", "fuaname_en": "Ede", "cityname_en": "Ede"}, {"id": "NLDGM0230", "text": "Elburg", "tl2_name_en": "Gelderland", "tl3_name_en": "Veluwe", "fuaname_en": "", "cityname_en": ""}, {"id": "NLDGM0232", "text": "Epe", "tl2_name_en": "Gelderland", "tl3_name_en": "Veluwe", "fuaname_en": "Apeldoorn", "cityname_en": ""}, {"id": "NLDGM0233", "text": "Ermelo", "tl2_name_en": "Gelderland", "tl3_name_en": "Veluwe", "fuaname_en": "", "cityname_en": ""}, {"id": "NLDGM0243", "text": "Harderwijk", "tl2_name_en": "Gelderland", "tl3_name_en": "Veluwe", "fuaname_en": "", "cityname_en": ""}, {"id": "NLDGM0244", "text": "Hattem", "tl2_name_en": "Gelderland", "tl3_name_en": "Veluwe", "fuaname_en": "Zwolle", "cityname_en": ""}, {"id": "NLDGM0246", "text": "Heerde", "tl2_name_en": "Gelderland", "tl3_name_en": "Veluwe", "fuaname_en": "Zwolle", "cityname_en": ""}, {"id": "NLDGM0252", "text": "Heumen", "tl2_name_en": "Gelderland", "tl3_name_en": "Arnhem/Nijmegen", "fuaname_en": "Nijmegen", "cityname_en": ""}, {"id": "NLDGM0262", "text": "Lochem", "tl2_name_en": "Gelderland", "tl3_name_en": "Achterhoek", "fuaname_en": "", "cityname_en": ""}, {"id": "NLDGM0263", "text": "Maasdriel", "tl2_name_en": "Gelderland", "tl3_name_en": "Zuidwest-Gelderland", "fuaname_en": "'s-Hertogenbosch", "cityname_en": ""}, {"id": "NLDGM0267", "text": "Nijkerk", "tl2_name_en": "Gelderland", "tl3_name_en": "Veluwe", "fuaname_en": "", "cityname_en": ""}, {"id": "NLDGM0268", "text": "Nijmegen", "tl2_name_en": "Gelderland", "tl3_name_en": "Arnhem/Nijmegen", "fuaname_en": "Nijmegen", "cityname_en": "Nijmegen"}, {"id": "NLDGM0269", "text": "Oldebroek", "tl2_name_en": "Gelderland", "tl3_name_en": "Veluwe", "fuaname_en": "Zwolle", "cityname_en": ""}, {"id": "NLDGM0273", "text": "Putten", "tl2_name_en": "Gelderland", "tl3_name_en": "Veluwe", "fuaname_en": "", "cityname_en": ""}, {"id": "NLDGM0274", "text": "Renkum", "tl2_name_en": "Gelderland", "tl3_name_en": "Arnhem/Nijmegen", "fuaname_en": "Arnhem", "cityname_en": ""}, {"id": "NLDGM0275", "text": "Rheden", "tl2_name_en": "Gelderland", "tl3_name_en": "Arnhem/Nijmegen", "fuaname_en": "Arnhem", "cityname_en": ""}, {"id": "NLDGM0277", "text": "Rozendaal", "tl2_name_en": "Gelderland", "tl3_name_en": "Arnhem/Nijmegen", "fuaname_en": "Arnhem", "cityname_en": ""}, {"id": "NLDGM0279", "text": "Scherpenzeel", "tl2_name_en": "Gelderland", "tl3_name_en": "Veluwe", "fuaname_en": "", "cityname_en": ""}, {"id": "NLDGM0281", "text": "Tiel", "tl2_name_en": "Gelderland", "tl3_name_en": "Zuidwest-Gelderland", "fuaname_en": "", "cityname_en": ""}, {"id": "NLDGM0285", "text": "Voorst", "tl2_name_en": "Gelderland", "tl3_name_en": "Veluwe", "fuaname_en": "Apeldoorn", "cityname_en": ""}, {"id": "NLDGM0289", "text": "Wageningen", "tl2_name_en": "Gelderland", "tl3_name_en": "Veluwe", "fuaname_en": "Ede", "cityname_en": "Ede"}, {"id": "NLDGM0293", "text": "Westervoort", "tl2_name_en": "Gelderland", "tl3_name_en": "Arnhem/Nijmegen", "fuaname_en": "Arnhem", "cityname_en": "Arnhem"}, {"id": "NLDGM0294", "text": "Winterswijk", "tl2_name_en": "Gelderland", "tl3_name_en": "Achterhoek", "fuaname_en": "", "cityname_en": ""}, {"id": "NLDGM0296", "text": "Wijchen", "tl2_name_en": "Gelderland", "tl3_name_en": "Arnhem/Nijmegen", "fuaname_en": "Nijmegen", "cityname_en": ""}, {"id": "NLDGM0297", "text": "Zaltbommel", "tl2_name_en": "Gelderland", "tl3_name_en": "Zuidwest-Gelderland", "fuaname_en": "", "cityname_en": ""}, {"id": "NLDGM0299", "text": "Zevenaar", "tl2_name_en": "Gelderland", "tl3_name_en": "Arnhem/Nijmegen", "fuaname_en": "Arnhem", "cityname_en": ""}, {"id": "NLDGM0301", "text": "Zutphen", "tl2_name_en": "Gelderland", "tl3_name_en": "Achterhoek", "fuaname_en": "", "cityname_en": ""}, {"id": "NLDGM0302", "text": "Nunspeet", "tl2_name_en": "Gelderland", "tl3_name_en": "Veluwe", "fuaname_en": "", "cityname_en": ""}, {"id": "NLDGM0668", "text": "West Maas en Waal", "tl2_name_en": "Gelderland", "tl3_name_en": "Zuidwest-Gelderland", "fuaname_en": "", "cityname_en": ""}, {"id": "NLDGM1509", "text": "Oude IJsselstreek", "tl2_name_en": "Gelderland", "tl3_name_en": "Achterhoek", "fuaname_en": "", "cityname_en": ""}, {"id": "NLDGM1586", "text": "Oost Gelre", "tl2_name_en": "Gelderland", "tl3_name_en": "Achterhoek", "fuaname_en": "", "cityname_en": ""}, {"id": "NLDGM1705", "text": "Lingewaard", "tl2_name_en": "Gelderland", "tl3_name_en": "Arnhem/Nijmegen", "fuaname_en": "Arnhem", "cityname_en": ""}, {"id": "NLDGM1734", "text": "Overbetuwe", "tl2_name_en": "Gelderland", "tl3_name_en": "Arnhem/Nijmegen", "fuaname_en": "Arnhem", "cityname_en": ""}, {"id": "NLDGM1740", "text": "Neder-Betuwe", "tl2_name_en": "Gelderland", "tl3_name_en": "Zuidwest-Gelderland", "fuaname_en": "", "cityname_en": ""}, {"id": "NLDGM1859", "text": "Berkelland", "tl2_name_en": "Gelderland", "tl3_name_en": "Achterhoek", "fuaname_en": "", "cityname_en": ""}, {"id": "NLDGM1876", "text": "Bronckhorst", "tl2_name_en": "Gelderland", "tl3_name_en": "Achterhoek", "fuaname_en": "", "cityname_en": ""}, {"id": "NLDGM1945", "text": "Berg en Dal", "tl2_name_en": "Gelderland", "tl3_name_en": "Arnhem/Nijmegen", "fuaname_en": "Nijmegen", "cityname_en": ""}, {"id": "NLDGM1955", "text": "Montferland", "tl2_name_en": "Gelderland", "tl3_name_en": "Achterhoek", "fuaname_en": "", "cityname_en": ""}, {"id": "NLDGM1960", "text": "West Betuwe", "tl2_name_en": "Gelderland", "tl3_name_en": "Zuidwest-Gelderland", "fuaname_en": "", "cityname_en": ""}]}, {"tl2_id": "NL31", "tl2_name_en": "Utrecht", "children": [{"id": "NLDGM0307", "text": "Amersfoort", "tl2_name_en": "Utrecht", "tl3_name_en": "Utrecht", "fuaname_en": "Amersfoort", "cityname_en": "Amersfoort"}, {"id": "NLDGM0308", "text": "Baarn", "tl2_name_en": "Utrecht", "tl3_name_en": "Utrecht", "fuaname_en": "Soest", "cityname_en": "Soest"}, {"id": "NLDGM0310", "text": "De Bilt", "tl2_name_en": "Utrecht", "tl3_name_en": "Utrecht", "fuaname_en": "Utrecht", "cityname_en": ""}, {"id": "NLDGM0312", "text": "Bunnik", "tl2_name_en": "Utrecht", "tl3_name_en": "Utrecht", "fuaname_en": "Utrecht", "cityname_en": ""}, {"id": "NLDGM0313", "text": "Bunschoten", "tl2_name_en": "Utrecht", "tl3_name_en": "Utrecht", "fuaname_en": "", "cityname_en": ""}, {"id": "NLDGM0317", "text": "Eemnes", "tl2_name_en": "Utrecht", "tl3_name_en": "Utrecht", "fuaname_en": "Amsterdam", "cityname_en": ""}, {"id": "NLDGM0321", "text": "Houten", "tl2_name_en": "Utrecht", "tl3_name_en": "Utrecht", "fuaname_en": "Utrecht", "cityname_en": ""}, {"id": "NLDGM0327", "text": "Leusden", "tl2_name_en": "Utrecht", "tl3_name_en": "Utrecht", "fuaname_en": "Amersfoort", "cityname_en": ""}, {"id": "NLDGM0331", "text": "Lopik", "tl2_name_en": "Utrecht", "tl3_name_en": "Utrecht", "fuaname_en": "Utrecht", "cityname_en": ""}, {"id": "NLDGM0335", "text": "Montfoort", "tl2_name_en": "Utrecht", "tl3_name_en": "Utrecht", "fuaname_en": "Utrecht", "cityname_en": ""}, {"id": "NLDGM0339", "text": "Renswoude", "tl2_name_en": "Utrecht", "tl3_name_en": "Utrecht", "fuaname_en": "Veenendaal", "cityname_en": ""}, {"id": "NLDGM0340", "text": "Rhenen", "tl2_name_en": "Utrecht", "tl3_name_en": "Utrecht", "fuaname_en": "Veenendaal", "cityname_en": ""}, {"id": "NLDGM0342", "text": "Soest", "tl2_name_en": "Utrecht", "tl3_name_en": "Utrecht", "fuaname_en": "Soest", "cityname_en": "Soest"}, {"id": "NLDGM0344", "text": "Utrecht", "tl2_name_en": "Utrecht", "tl3_name_en": "Utrecht", "fuaname_en": "Utrecht", "cityname_en": "Utrecht"}, {"id": "NLDGM0345", "text": "Veenendaal", "tl2_name_en": "Utrecht", "tl3_name_en": "Utrecht", "fuaname_en": "Veenendaal", "cityname_en": "Veenendaal"}, {"id": "NLDGM0351", "text": "Woudenberg", "tl2_name_en": "Utrecht", "tl3_name_en": "Utrecht", "fuaname_en": "", "cityname_en": ""}, {"id": "NLDGM0352", "text": "Wijk bij Duurstede", "tl2_name_en": "Utrecht", "tl3_name_en": "Utrecht", "fuaname_en": "Utrecht", "cityname_en": ""}, {"id": "NLDGM0353", "text": "IJsselstein", "tl2_name_en": "Utrecht", "tl3_name_en": "Utrecht", "fuaname_en": "Utrecht", "cityname_en": "Utrecht"}, {"id": "NLDGM0355", "text": "Zeist", "tl2_name_en": "Utrecht", "tl3_name_en": "Utrecht", "fuaname_en": "Utrecht", "cityname_en": ""}, {"id": "NLDGM0356", "text": "Nieuwegein", "tl2_name_en": "Utrecht", "tl3_name_en": "Utrecht", "fuaname_en": "Utrecht", "cityname_en": "Utrecht"}, {"id": "NLDGM0589", "text": "Oudewater", "tl2_name_en": "Utrecht", "tl3_name_en": "Utrecht", "fuaname_en": "Utrecht", "cityname_en": ""}, {"id": "NLDGM0632", "text": "Woerden", "tl2_name_en": "Utrecht", "tl3_name_en": "Utrecht", "fuaname_en": "Utrecht", "cityname_en": ""}, {"id": "NLDGM0736", "text": "De Ronde Venen", "tl2_name_en": "Utrecht", "tl3_name_en": "Utrecht", "fuaname_en": "Amsterdam", "cityname_en": ""}, {"id": "NLDGM1581", "text": "Utrechtse Heuvelrug", "tl2_name_en": "Utrecht", "tl3_name_en": "Utrecht", "fuaname_en": "Utrecht", "cityname_en": ""}, {"id": "NLDGM1904", "text": "Stichtse Vecht", "tl2_name_en": "Utrecht", "tl3_name_en": "Utrecht", "fuaname_en": "Utrecht", "cityname_en": ""}]}, {"tl2_id": "NL32", "tl2_name_en": "North Holland", "children": [{"id": "NLDGM0358", "text": "Aalsmeer", "tl2_name_en": "North Holland", "tl3_name_en": "Groot-Amsterdam", "fuaname_en": "Amsterdam", "cityname_en": ""}, {"id": "NLDGM0361", "text": "Alkmaar", "tl2_name_en": "North Holland", "tl3_name_en": "Alkmaar en omgeving", "fuaname_en": "Alkmaar", "cityname_en": "Alkmaar"}, {"id": "NLDGM0362", "text": "Amstelveen", "tl2_name_en": "North Holland", "tl3_name_en": "Groot-Amsterdam", "fuaname_en": "Amsterdam", "cityname_en": "Amsterdam"}, {"id": "NLDGM0363", "text": "Amsterdam", "tl2_name_en": "North Holland", "tl3_name_en": "Groot-Amsterdam", "fuaname_en": "Amsterdam", "cityname_en": "Amsterdam"}, {"id": "NLDGM0373", "text": "Bergen (NH.)", "tl2_name_en": "North Holland", "tl3_name_en": "Alkmaar en omgeving", "fuaname_en": "Alkmaar", "cityname_en": ""}, {"id": "NLDGM0375", "text": "Beverwijk", "tl2_name_en": "North Holland", "tl3_name_en": "IJmond", "fuaname_en": "Amsterdam", "cityname_en": "Heemskerk"}, {"id": "NLDGM0376", "text": "Blaricum", "tl2_name_en": "North Holland", "tl3_name_en": "Het Gooi en Vechtstreek", "fuaname_en": "Amsterdam", "cityname_en": ""}, {"id": "NLDGM0377", "text": "Bloemendaal", "tl2_name_en": "North Holland", "tl3_name_en": "Agglomeratie Haarlem", "fuaname_en": "Amsterdam", "cityname_en": "Haarlem"}, {"id": "NLDGM0383", "text": "Castricum", "tl2_name_en": "North Holland", "tl3_name_en": "IJmond", "fuaname_en": "Amsterdam", "cityname_en": ""}, {"id": "NLDGM0384", "text": "Diemen", "tl2_name_en": "North Holland", "tl3_name_en": "Groot-Amsterdam", "fuaname_en": "Amsterdam", "cityname_en": "Amsterdam"}, {"id": "NLDGM0385", "text": "Edam-Volendam", "tl2_name_en": "North Holland", "tl3_name_en": "Groot-Amsterdam", "fuaname_en": "Amsterdam", "cityname_en": ""}, {"id": "NLDGM0388", "text": "Enkhuizen", "tl2_name_en": "North Holland", "tl3_name_en": "Kop van Noord-Holland", "fuaname_en": "Amsterdam", "cityname_en": ""}, {"id": "NLDGM0392", "text": "Haarlem", "tl2_name_en": "North Holland", "tl3_name_en": "Agglomeratie Haarlem", "fuaname_en": "Amsterdam", "cityname_en": "Haarlem"}, {"id": "NLDGM0394", "text": "Haarlemmermeer", "tl2_name_en": "North Holland", "tl3_name_en": "Groot-Amsterdam", "fuaname_en": "Amsterdam", "cityname_en": "Haarlemmermeer"}, {"id": "NLDGM0396", "text": "Heemskerk", "tl2_name_en": "North Holland", "tl3_name_en": "IJmond", "fuaname_en": "Amsterdam", "cityname_en": "Heemskerk"}, {"id": "NLDGM0397", "text": "Heemstede", "tl2_name_en": "North Holland", "tl3_name_en": "Agglomeratie Haarlem", "fuaname_en": "Amsterdam", "cityname_en": "Haarlem"}, {"id": "NLDGM0399", "text": "Heiloo", "tl2_name_en": "North Holland", "tl3_name_en": "Alkmaar en omgeving", "fuaname_en": "Alkmaar", "cityname_en": "Alkmaar"}, {"id": "NLDGM0400", "text": "Den Helder", "tl2_name_en": "North Holland", "tl3_name_en": "Kop van Noord-Holland", "fuaname_en": "", "cityname_en": ""}, {"id": "NLDGM0402", "text": "Hilversum", "tl2_name_en": "North Holland", "tl3_name_en": "Het Gooi en Vechtstreek", "fuaname_en": "Amsterdam", "cityname_en": "Hilversum"}, {"id": "NLDGM0405", "text": "Hoorn", "tl2_name_en": "North Holland", "tl3_name_en": "Kop van Noord-Holland", "fuaname_en": "Amsterdam", "cityname_en": "Hoorn"}, {"id": "NLDGM0406", "text": "Huizen", "tl2_name_en": "North Holland", "tl3_name_en": "Het Gooi en Vechtstreek", "fuaname_en": "Amsterdam", "cityname_en": ""}, {"id": "NLDGM0415", "text": "Landsmeer", "tl2_name_en": "North Holland", "tl3_name_en": "Groot-Amsterdam", "fuaname_en": "Amsterdam", "cityname_en": ""}, {"id": "NLDGM0417", "text": "Laren", "tl2_name_en": "North Holland", "tl3_name_en": "Het Gooi en Vechtstreek", "fuaname_en": "Amsterdam", "cityname_en": ""}, {"id": "NLDGM0420", "text": "Medemblik", "tl2_name_en": "North Holland", "tl3_name_en": "Kop van Noord-Holland", "fuaname_en": "Amsterdam", "cityname_en": ""}, {"id": "NLDGM0431", "text": "Oostzaan", "tl2_name_en": "North Holland", "tl3_name_en": "Groot-Amsterdam", "fuaname_en": "Amsterdam", "cityname_en": ""}, {"id": "NLDGM0432", "text": "Opmeer", "tl2_name_en": "North Holland", "tl3_name_en": "Kop van Noord-Holland", "fuaname_en": "Amsterdam", "cityname_en": ""}, {"id": "NLDGM0437", "text": "Ouder-Amstel", "tl2_name_en": "North Holland", "tl3_name_en": "Groot-Amsterdam", "fuaname_en": "Amsterdam", "cityname_en": "Amsterdam"}, {"id": "NLDGM0439", "text": "Purmerend", "tl2_name_en": "North Holland", "tl3_name_en": "Groot-Amsterdam", "fuaname_en": "Amsterdam", "cityname_en": "Purmerend"}, {"id": "NLDGM0441", "text": "Schagen", "tl2_name_en": "North Holland", "tl3_name_en": "Kop van Noord-Holland", "fuaname_en": "Alkmaar", "cityname_en": ""}, {"id": "NLDGM0448", "text": "Texel", "tl2_name_en": "North Holland", "tl3_name_en": "Kop van Noord-Holland", "fuaname_en": "", "cityname_en": ""}, {"id": "NLDGM0450", "text": "Uitgeest", "tl2_name_en": "North Holland", "tl3_name_en": "IJmond", "fuaname_en": "Amsterdam", "cityname_en": "Heemskerk"}, {"id": "NLDGM0451", "text": "Uithoorn", "tl2_name_en": "North Holland", "tl3_name_en": "Groot-Amsterdam", "fuaname_en": "Amsterdam", "cityname_en": ""}, {"id": "NLDGM0453", "text": "Velsen", "tl2_name_en": "North Holland", "tl3_name_en": "IJmond", "fuaname_en": "Amsterdam", "cityname_en": "Haarlem"}, {"id": "NLDGM0473", "text": "Zandvoort", "tl2_name_en": "North Holland", "tl3_name_en": "Agglomeratie Haarlem", "fuaname_en": "Amsterdam", "cityname_en": ""}, {"id": "NLDGM0479", "text": "Zaanstad", "tl2_name_en": "North Holland", "tl3_name_en": "Zaanstreek", "fuaname_en": "Amsterdam", "cityname_en": "Zaanstad"}, {"id": "NLDGM0498", "text": "Drechterland", "tl2_name_en": "North Holland", "tl3_name_en": "Kop van Noord-Holland", "fuaname_en": "Amsterdam", "cityname_en": ""}, {"id": "NLDGM0532", "text": "Stede Broec", "tl2_name_en": "North Holland", "tl3_name_en": "Kop van Noord-Holland", "fuaname_en": "Amsterdam", "cityname_en": ""}, {"id": "NLDGM0852", "text": "Waterland", "tl2_name_en": "North Holland", "tl3_name_en": "Groot-Amsterdam", "fuaname_en": "Amsterdam", "cityname_en": ""}, {"id": "NLDGM0880", "text": "Wormerland", "tl2_name_en": "North Holland", "tl3_name_en": "Zaanstreek", "fuaname_en": "Amsterdam", "cityname_en": ""}, {"id": "NLDGM1598", "text": "Koggenland", "tl2_name_en": "North Holland", "tl3_name_en": "Kop van Noord-Holland", "fuaname_en": "Amsterdam", "cityname_en": ""}, {"id": "NLDGM1696", "text": "Wijdemeren", "tl2_name_en": "North Holland", "tl3_name_en": "Het Gooi en Vechtstreek", "fuaname_en": "Amsterdam", "cityname_en": ""}, {"id": "NLDGM1911", "text": "Hollands Kroon", "tl2_name_en": "North Holland", "tl3_name_en": "Kop van Noord-Holland", "fuaname_en": "Amsterdam", "cityname_en": ""}, {"id": "NLDGM1942", "text": "Gooise Meren", "tl2_name_en": "North Holland", "tl3_name_en": "Het Gooi en Vechtstreek", "fuaname_en": "Amsterdam", "cityname_en": ""}, {"id": "NLDGM1980", "text": "Dijk en Waard", "tl2_name_en": "North Holland", "tl3_name_en": "Alkmaar en omgeving", "fuaname_en": "Alkmaar", "cityname_en": "Alkmaar"}]}, {"tl2_id": "NL33", "tl2_name_en": "South Holland", "children": [{"id": "NLDGM0482", "text": "Alblasserdam", "tl2_name_en": "South Holland", "tl3_name_en": "Zuidoost-Zuid-Holland", "fuaname_en": "Rotterdam", "cityname_en": "Rotterdam"}, {"id": "NLDGM0484", "text": "Alphen aan den Rijn", "tl2_name_en": "South Holland", "tl3_name_en": "Oost-Zuid-Holland", "fuaname_en": "Alphen aan den Rijn", "cityname_en": "Alphen aan den Rijn"}, {"id": "NLDGM0489", "text": "Barendrecht", "tl2_name_en": "South Holland", "tl3_name_en": "Groot-Rijnmond", "fuaname_en": "Rotterdam", "cityname_en": "Rotterdam"}, {"id": "NLDGM0502", "text": "Capelle aan den IJssel", "tl2_name_en": "South Holland", "tl3_name_en": "Groot-Rijnmond", "fuaname_en": "Rotterdam", "cityname_en": "Rotterdam"}, {"id": "NLDGM0503", "text": "Delft", "tl2_name_en": "South Holland", "tl3_name_en": "Delft en Westland", "fuaname_en": "'s-Gravenhage", "cityname_en": "'s-Gravenhage"}, {"id": "NLDGM0505", "text": "Dordrecht", "tl2_name_en": "South Holland", "tl3_name_en": "Zuidoost-Zuid-Holland", "fuaname_en": "Rotterdam", "cityname_en": "Rotterdam"}, {"id": "NLDGM0512", "text": "Gorinchem", "tl2_name_en": "South Holland", "tl3_name_en": "Zuidoost-Zuid-Holland", "fuaname_en": "", "cityname_en": ""}, {"id": "NLDGM0513", "text": "Gouda", "tl2_name_en": "South Holland", "tl3_name_en": "Oost-Zuid-Holland", "fuaname_en": "Gouda", "cityname_en": "Gouda"}, {"id": "NLDGM0518", "text": "'s-Gravenhage", "tl2_name_en": "South Holland", "tl3_name_en": "Agglomeratie 's-Gravenhage", "fuaname_en": "'s-Gravenhage", "cityname_en": "'s-Gravenhage"}, {"id": "NLDGM0523", "text": "Hardinxveld-Giessendam", "tl2_name_en": "South Holland", "tl3_name_en": "Zuidoost-Zuid-Holland", "fuaname_en": "Rotterdam", "cityname_en": ""}, {"id": "NLDGM0531", "text": "Hendrik-Ido-Ambacht", "tl2_name_en": "South Holland", "tl3_name_en": "Zuidoost-Zuid-Holland", "fuaname_en": "Rotterdam", "cityname_en": "Rotterdam"}, {"id": "NLDGM0534", "text": "Hillegom", "tl2_name_en": "South Holland", "tl3_name_en": "Agglomeratie Leiden en Bollenstreek", "fuaname_en": "Amsterdam", "cityname_en": ""}, {"id": "NLDGM0537", "text": "Katwijk", "tl2_name_en": "South Holland", "tl3_name_en": "Agglomeratie Leiden en Bollenstreek", "fuaname_en": "Leiden", "cityname_en": "Leiden"}, {"id": "NLDGM0542", "text": "Krimpen aan den IJssel", "tl2_name_en": "South Holland", "tl3_name_en": "Groot-Rijnmond", "fuaname_en": "Rotterdam", "cityname_en": "Rotterdam"}, {"id": "NLDGM0546", "text": "Leiden", "tl2_name_en": "South Holland", "tl3_name_en": "Agglomeratie Leiden en Bollenstreek", "fuaname_en": "Leiden", "cityname_en": "Leiden"}, {"id": "NLDGM0547", "text": "Leiderdorp", "tl2_name_en": "South Holland", "tl3_name_en": "Agglomeratie Leiden en Bollenstreek", "fuaname_en": "Leiden", "cityname_en": "Leiden"}, {"id": "NLDGM0553", "text": "Lisse", "tl2_name_en": "South Holland", "tl3_name_en": "Agglomeratie Leiden en Bollenstreek", "fuaname_en": "Amsterdam", "cityname_en": ""}, {"id": "NLDGM0556", "text": "Maassluis", "tl2_name_en": "South Holland", "tl3_name_en": "Groot-Rijnmond", "fuaname_en": "Rotterdam", "cityname_en": ""}, {"id": "NLDGM0569", "text": "Nieuwkoop", "tl2_name_en": "South Holland", "tl3_name_en": "Oost-Zuid-Holland", "fuaname_en": "Amsterdam", "cityname_en": ""}, {"id": "NLDGM0575", "text": "Noordwijk", "tl2_name_en": "South Holland", "tl3_name_en": "Agglomeratie Leiden en Bollenstreek", "fuaname_en": "Leiden", "cityname_en": ""}, {"id": "NLDGM0579", "text": "Oegstgeest", "tl2_name_en": "South Holland", "tl3_name_en": "Agglomeratie Leiden en Bollenstreek", "fuaname_en": "Leiden", "cityname_en": "Leiden"}, {"id": "NLDGM0590", "text": "Papendrecht", "tl2_name_en": "South Holland", "tl3_name_en": "Zuidoost-Zuid-Holland", "fuaname_en": "Rotterdam", "cityname_en": "Rotterdam"}, {"id": "NLDGM0597", "text": "Ridderkerk", "tl2_name_en": "South Holland", "tl3_name_en": "Groot-Rijnmond", "fuaname_en": "Rotterdam", "cityname_en": "Rotterdam"}, {"id": "NLDGM0599", "text": "Rotterdam", "tl2_name_en": "South Holland", "tl3_name_en": "Groot-Rijnmond", "fuaname_en": "Rotterdam", "cityname_en": "Rotterdam"}, {"id": "NLDGM0603", "text": "Rijswijk", "tl2_name_en": "South Holland", "tl3_name_en": "Agglomeratie 's-Gravenhage", "fuaname_en": "'s-Gravenhage", "cityname_en": "'s-Gravenhage"}, {"id": "NLDGM0606", "text": "Schiedam", "tl2_name_en": "South Holland", "tl3_name_en": "Groot-Rijnmond", "fuaname_en": "Rotterdam", "cityname_en": "Rotterdam"}, {"id": "NLDGM0610", "text": "Sliedrecht", "tl2_name_en": "South Holland", "tl3_name_en": "Zuidoost-Zuid-Holland", "fuaname_en": "Rotterdam", "cityname_en": ""}, {"id": "NLDGM0613", "text": "Albrandswaard", "tl2_name_en": "South Holland", "tl3_name_en": "Groot-Rijnmond", "fuaname_en": "Rotterdam", "cityname_en": "Nissewaard"}, {"id": "NLDGM0622", "text": "Vlaardingen", "tl2_name_en": "South Holland", "tl3_name_en": "Groot-Rijnmond", "fuaname_en": "Rotterdam", "cityname_en": "Rotterdam"}, {"id": "NLDGM0626", "text": "Voorschoten", "tl2_name_en": "South Holland", "tl3_name_en": "Agglomeratie Leiden en Bollenstreek", "fuaname_en": "Leiden", "cityname_en": "Leiden"}, {"id": "NLDGM0627", "text": "Waddinxveen", "tl2_name_en": "South Holland", "tl3_name_en": "Oost-Zuid-Holland", "fuaname_en": "", "cityname_en": ""}, {"id": "NLDGM0629", "text": "Wassenaar", "tl2_name_en": "South Holland", "tl3_name_en": "Agglomeratie 's-Gravenhage", "fuaname_en": "'s-Gravenhage", "cityname_en": ""}, {"id": "NLDGM0637", "text": "Zoetermeer", "tl2_name_en": "South Holland", "tl3_name_en": "Agglomeratie 's-Gravenhage", "fuaname_en": "'s-Gravenhage", "cityname_en": "Zoetermeer"}, {"id": "NLDGM0638", "text": "Zoeterwoude", "tl2_name_en": "South Holland", "tl3_name_en": "Agglomeratie Leiden en Bollenstreek", "fuaname_en": "Leiden", "cityname_en": ""}, {"id": "NLDGM0642", "text": "Zwijndrecht", "tl2_name_en": "South Holland", "tl3_name_en": "Zuidoost-Zuid-Holland", "fuaname_en": "Rotterdam", "cityname_en": "Rotterdam"}, {"id": "NLDGM1525", "text": "Teylingen", "tl2_name_en": "South Holland", "tl3_name_en": "Agglomeratie Leiden en Bollenstreek", "fuaname_en": "Leiden", "cityname_en": ""}, {"id": "NLDGM1621", "text": "Lansingerland", "tl2_name_en": "South Holland", "tl3_name_en": "Groot-Rijnmond", "fuaname_en": "Rotterdam", "cityname_en": ""}, {"id": "NLDGM1783", "text": "Westland", "tl2_name_en": "South Holland", "tl3_name_en": "Delft en Westland", "fuaname_en": "'s-Gravenhage", "cityname_en": ""}, {"id": "NLDGM1842", "text": "Midden-Delfland", "tl2_name_en": "South Holland", "tl3_name_en": "Delft en Westland", "fuaname_en": "'s-Gravenhage", "cityname_en": ""}, {"id": "NLDGM1884", "text": "Kaag en Braassem", "tl2_name_en": "South Holland", "tl3_name_en": "Agglomeratie Leiden en Bollenstreek", "fuaname_en": "Amsterdam", "cityname_en": ""}, {"id": "NLDGM1892", "text": "Zuidplas", "tl2_name_en": "South Holland", "tl3_name_en": "Groot-Rijnmond", "fuaname_en": "Rotterdam", "cityname_en": ""}, {"id": "NLDGM1901", "text": "Bodegraven-Reeuwijk", "tl2_name_en": "South Holland", "tl3_name_en": "Oost-Zuid-Holland", "fuaname_en": "", "cityname_en": ""}, {"id": "NLDGM1916", "text": "Leidschendam-Voorburg", "tl2_name_en": "South Holland", "tl3_name_en": "Agglomeratie 's-Gravenhage", "fuaname_en": "'s-Gravenhage", "cityname_en": "'s-Gravenhage"}, {"id": "NLDGM1924", "text": "Goeree-Overflakkee", "tl2_name_en": "South Holland", "tl3_name_en": "Groot-Rijnmond", "fuaname_en": "Rotterdam", "cityname_en": ""}, {"id": "NLDGM1926", "text": "Pijnacker-Nootdorp", "tl2_name_en": "South Holland", "tl3_name_en": "Agglomeratie 's-Gravenhage", "fuaname_en": "'s-Gravenhage", "cityname_en": ""}, {"id": "NLDGM1930", "text": "Nissewaard", "tl2_name_en": "South Holland", "tl3_name_en": "Groot-Rijnmond", "fuaname_en": "Rotterdam", "cityname_en": "Nissewaard"}, {"id": "NLDGM1931", "text": "Krimpenerwaard", "tl2_name_en": "South Holland", "tl3_name_en": "Oost-Zuid-Holland", "fuaname_en": "Rotterdam", "cityname_en": ""}, {"id": "NLDGM1961", "text": "Vijfheerenlanden", "tl2_name_en": "South Holland", "tl3_name_en": "Zuidoost-Zuid-Holland", "fuaname_en": "", "cityname_en": ""}, {"id": "NLDGM1963", "text": "Hoeksche Waard", "tl2_name_en": "South Holland", "tl3_name_en": "Groot-Rijnmond", "fuaname_en": "Rotterdam", "cityname_en": ""}, {"id": "NLDGM1978", "text": "Molenlanden", "tl2_name_en": "South Holland", "tl3_name_en": "Zuidoost-Zuid-Holland", "fuaname_en": "", "cityname_en": ""}, {"id": "NLDGM1992", "text": "Voorne aan Zee", "tl2_name_en": "South Holland", "tl3_name_en": "Groot-Rijnmond", "fuaname_en": "Rotterdam", "cityname_en": ""}]}, {"tl2_id": "NL34", "tl2_name_en": "Zeeland", "children": [{"id": "NLDGM0654", "text": "Borsele", "tl2_name_en": "Zeeland", "tl3_name_en": "Overig Zeeland", "fuaname_en": "", "cityname_en": ""}, {"id": "NLDGM0664", "text": "Goes", "tl2_name_en": "Zeeland", "tl3_name_en": "Overig Zeeland", "fuaname_en": "", "cityname_en": ""}, {"id": "NLDGM0677", "text": "Hulst", "tl2_name_en": "Zeeland", "tl3_name_en": "Zeeuwsch-Vlaanderen", "fuaname_en": "", "cityname_en": ""}, {"id": "NLDGM0678", "text": "Kapelle", "tl2_name_en": "Zeeland", "tl3_name_en": "Overig Zeeland", "fuaname_en": "", "cityname_en": ""}, {"id": "NLDGM0687", "text": "Middelburg", "tl2_name_en": "Zeeland", "tl3_name_en": "Overig Zeeland", "fuaname_en": "Middelburg \u00a0\u00a0\u00a0\u00a0\u00a0\u00a0", "cityname_en": "Middelburg \u00a0\u00a0\u00a0\u00a0\u00a0\u00a0"}, {"id": "NLDGM0703", "text": "Reimerswaal", "tl2_name_en": "Zeeland", "tl3_name_en": "Overig Zeeland", "fuaname_en": "", "cityname_en": ""}, {"id": "NLDGM0715", "text": "Terneuzen", "tl2_name_en": "Zeeland", "tl3_name_en": "Zeeuwsch-Vlaanderen", "fuaname_en": "", "cityname_en": ""}, {"id": "NLDGM0716", "text": "Tholen", "tl2_name_en": "Zeeland", "tl3_name_en": "Overig Zeeland", "fuaname_en": "Bergen op Zoom", "cityname_en": ""}, {"id": "NLDGM0717", "text": "Veere", "tl2_name_en": "Zeeland", "tl3_name_en": "Overig Zeeland", "fuaname_en": "Middelburg \u00a0\u00a0\u00a0\u00a0\u00a0\u00a0", "cityname_en": ""}, {"id": "NLDGM0718", "text": "Vlissingen", "tl2_name_en": "Zeeland", "tl3_name_en": "Overig Zeeland", "fuaname_en": "Middelburg \u00a0\u00a0\u00a0\u00a0\u00a0\u00a0", "cityname_en": "Middelburg \u00a0\u00a0\u00a0\u00a0\u00a0\u00a0"}, {"id": "NLDGM1676", "text": "Schouwen-Duiveland", "tl2_name_en": "Zeeland", "tl3_name_en": "Overig Zeeland", "fuaname_en": "", "cityname_en": ""}, {"id": "NLDGM1695", "text": "Noord-Beveland", "tl2_name_en": "Zeeland", "tl3_name_en": "Overig Zeeland", "fuaname_en": "", "cityname_en": ""}, {"id": "NLDGM1714", "text": "Sluis", "tl2_name_en": "Zeeland", "tl3_name_en": "Zeeuwsch-Vlaanderen", "fuaname_en": "", "cityname_en": ""}]}, {"tl2_id": "NL41", "tl2_name_en": "North Brabant", "children": [{"id": "NLDGM0743", "text": "Asten", "tl2_name_en": "North Brabant", "tl3_name_en": "Zuidoost-Noord-Brabant", "fuaname_en": "Eindhoven", "cityname_en": ""}, {"id": "NLDGM0744", "text": "Baarle-Nassau", "tl2_name_en": "North Brabant", "tl3_name_en": "Midden-Noord-Brabant", "fuaname_en": "Breda", "cityname_en": ""}, {"id": "NLDGM0748", "text": "Bergen op Zoom", "tl2_name_en": "North Brabant", "tl3_name_en": "West-Noord-Brabant", "fuaname_en": "Bergen op Zoom", "cityname_en": "Bergen op Zoom"}, {"id": "NLDGM0753", "text": "Best", "tl2_name_en": "North Brabant", "tl3_name_en": "Zuidoost-Noord-Brabant", "fuaname_en": "Eindhoven", "cityname_en": ""}, {"id": "NLDGM0755", "text": "Boekel", "tl2_name_en": "North Brabant", "tl3_name_en": "Noordoost-Noord-Brabant", "fuaname_en": "", "cityname_en": ""}, {"id": "NLDGM0757", "text": "Boxtel", "tl2_name_en": "North Brabant", "tl3_name_en": "Noordoost-Noord-Brabant", "fuaname_en": "", "cityname_en": ""}, {"id": "NLDGM0758", "text": "Breda", "tl2_name_en": "North Brabant", "tl3_name_en": "West-Noord-Brabant", "fuaname_en": "Breda", "cityname_en": "Breda"}, {"id": "NLDGM0762", "text": "Deurne", "tl2_name_en": "North Brabant", "tl3_name_en": "Zuidoost-Noord-Brabant", "fuaname_en": "Eindhoven", "cityname_en": ""}, {"id": "NLDGM0766", "text": "Dongen", "tl2_name_en": "North Brabant", "tl3_name_en": "Midden-Noord-Brabant", "fuaname_en": "", "cityname_en": ""}, {"id": "NLDGM0770", "text": "Eersel", "tl2_name_en": "North Brabant", "tl3_name_en": "Zuidoost-Noord-Brabant", "fuaname_en": "Eindhoven", "cityname_en": ""}, {"id": "NLDGM0772", "text": "Eindhoven", "tl2_name_en": "North Brabant", "tl3_name_en": "Zuidoost-Noord-Brabant", "fuaname_en": "Eindhoven", "cityname_en": "Eindhoven"}, {"id": "NLDGM0777", "text": "Etten-Leur", "tl2_name_en": "North Brabant", "tl3_name_en": "West-Noord-Brabant", "fuaname_en": "Breda", "cityname_en": ""}, {"id": "NLDGM0779", "text": "Geertruidenberg", "tl2_name_en": "North Brabant", "tl3_name_en": "West-Noord-Brabant", "fuaname_en": "", "cityname_en": ""}, {"id": "NLDGM0784", "text": "Gilze en Rijen", "tl2_name_en": "North Brabant", "tl3_name_en": "Midden-Noord-Brabant", "fuaname_en": "Breda", "cityname_en": ""}, {"id": "NLDGM0785", "text": "Goirle", "tl2_name_en": "North Brabant", "tl3_name_en": "Midden-Noord-Brabant", "fuaname_en": "Tilburg", "cityname_en": ""}, {"id": "NLDGM0794", "text": "Helmond", "tl2_name_en": "North Brabant", "tl3_name_en": "Zuidoost-Noord-Brabant", "fuaname_en": "Eindhoven", "cityname_en": "Helmond"}, {"id": "NLDGM0796", "text": "'s-Hertogenbosch", "tl2_name_en": "North Brabant", "tl3_name_en": "Noordoost-Noord-Brabant", "fuaname_en": "'s-Hertogenbosch", "cityname_en": "'s-Hertogenbosch"}, {"id": "NLDGM0797", "text": "Heusden", "tl2_name_en": "North Brabant", "tl3_name_en": "Noordoost-Noord-Brabant", "fuaname_en": "'s-Hertogenbosch", "cityname_en": ""}, {"id": "NLDGM0798", "text": "Hilvarenbeek", "tl2_name_en": "North Brabant", "tl3_name_en": "Midden-Noord-Brabant", "fuaname_en": "Tilburg", "cityname_en": ""}, {"id": "NLDGM0809", "text": "Loon op Zand", "tl2_name_en": "North Brabant", "tl3_name_en": "Midden-Noord-Brabant", "fuaname_en": "Tilburg", "cityname_en": ""}, {"id": "NLDGM0820", "text": "Nuenen, Gerwen en Nederwetten", "tl2_name_en": "North Brabant", "tl3_name_en": "Zuidoost-Noord-Brabant", "fuaname_en": "Eindhoven", "cityname_en": ""}, {"id": "NLDGM0823", "text": "Oirschot", "tl2_name_en": "North Brabant", "tl3_name_en": "Zuidoost-Noord-Brabant", "fuaname_en": "Eindhoven", "cityname_en": ""}, {"id": "NLDGM0824", "text": "Oisterwijk", "tl2_name_en": "North Brabant", "tl3_name_en": "Midden-Noord-Brabant", "fuaname_en": "Tilburg", "cityname_en": ""}, {"id": "NLDGM0826", "text": "Oosterhout", "tl2_name_en": "North Brabant", "tl3_name_en": "West-Noord-Brabant", "fuaname_en": "Breda", "cityname_en": ""}, {"id": "NLDGM0828", "text": "Oss", "tl2_name_en": "North Brabant", "tl3_name_en": "Noordoost-Noord-Brabant", "fuaname_en": "Oss", "cityname_en": "Oss"}, {"id": "NLDGM0840", "text": "Rucphen", "tl2_name_en": "North Brabant", "tl3_name_en": "West-Noord-Brabant", "fuaname_en": "Roosendaal", "cityname_en": ""}, {"id": "NLDGM0845", "text": "Sint-Michielsgestel", "tl2_name_en": "North Brabant", "tl3_name_en": "Noordoost-Noord-Brabant", "fuaname_en": "'s-Hertogenbosch", "cityname_en": ""}, {"id": "NLDGM0847", "text": "Someren", "tl2_name_en": "North Brabant", "tl3_name_en": "Zuidoost-Noord-Brabant", "fuaname_en": "Eindhoven", "cityname_en": ""}, {"id": "NLDGM0848", "text": "Son en Breugel", "tl2_name_en": "North Brabant", "tl3_name_en": "Zuidoost-Noord-Brabant", "fuaname_en": "Eindhoven", "cityname_en": ""}, {"id": "NLDGM0851", "text": "Steenbergen", "tl2_name_en": "North Brabant", "tl3_name_en": "West-Noord-Brabant", "fuaname_en": "", "cityname_en": ""}, {"id": "NLDGM0855", "text": "Tilburg", "tl2_name_en": "North Brabant", "tl3_name_en": "Midden-Noord-Brabant", "fuaname_en": "Tilburg", "cityname_en": "Tilburg"}, {"id": "NLDGM0858", "text": "Valkenswaard", "tl2_name_en": "North Brabant", "tl3_name_en": "Zuidoost-Noord-Brabant", "fuaname_en": "Eindhoven", "cityname_en": ""}, {"id": "NLDGM0861", "text": "Veldhoven", "tl2_name_en": "North Brabant", "tl3_name_en": "Zuidoost-Noord-Brabant", "fuaname_en": "Eindhoven", "cityname_en": "Eindhoven"}, {"id": "NLDGM0865", "text": "Vught", "tl2_name_en": "North Brabant", "tl3_name_en": "Noordoost-Noord-Brabant", "fuaname_en": "'s-Hertogenbosch", "cityname_en": ""}, {"id": "NLDGM0866", "text": "Waalre", "tl2_name_en": "North Brabant", "tl3_name_en": "Zuidoost-Noord-Brabant", "fuaname_en": "Eindhoven", "cityname_en": ""}, {"id": "NLDGM0867", "text": "Waalwijk", "tl2_name_en": "North Brabant", "tl3_name_en": "Midden-Noord-Brabant", "fuaname_en": "", "cityname_en": ""}, {"id": "NLDGM0873", "text": "Woensdrecht", "tl2_name_en": "North Brabant", "tl3_name_en": "West-Noord-Brabant", "fuaname_en": "Bergen op Zoom", "cityname_en": ""}, {"id": "NLDGM0879", "text": "Zundert", "tl2_name_en": "North Brabant", "tl3_name_en": "West-Noord-Brabant", "fuaname_en": "Breda", "cityname_en": ""}, {"id": "NLDGM1652", "text": "Gemert-Bakel", "tl2_name_en": "North Brabant", "tl3_name_en": "Zuidoost-Noord-Brabant", "fuaname_en": "Eindhoven", "cityname_en": ""}, {"id": "NLDGM1655", "text": "Halderberge", "tl2_name_en": "North Brabant", "tl3_name_en": "West-Noord-Brabant", "fuaname_en": "Roosendaal", "cityname_en": ""}, {"id": "NLDGM1658", "text": "Heeze-Leende", "tl2_name_en": "North Brabant", "tl3_name_en": "Zuidoost-Noord-Brabant", "fuaname_en": "Eindhoven", "cityname_en": ""}, {"id": "NLDGM1659", "text": "Laarbeek", "tl2_name_en": "North Brabant", "tl3_name_en": "Zuidoost-Noord-Brabant", "fuaname_en": "Eindhoven", "cityname_en": ""}, {"id": "NLDGM1667", "text": "Reusel-De Mierden", "tl2_name_en": "North Brabant", "tl3_name_en": "Zuidoost-Noord-Brabant", "fuaname_en": "", "cityname_en": ""}, {"id": "NLDGM1674", "text": "Roosendaal", "tl2_name_en": "North Brabant", "tl3_name_en": "West-Noord-Brabant", "fuaname_en": "Roosendaal", "cityname_en": "Roosendaal"}, {"id": "NLDGM1706", "text": "Cranendonck", "tl2_name_en": "North Brabant", "tl3_name_en": "Zuidoost-Noord-Brabant", "fuaname_en": "Eindhoven", "cityname_en": ""}, {"id": "NLDGM1709", "text": "Moerdijk", "tl2_name_en": "North Brabant", "tl3_name_en": "West-Noord-Brabant", "fuaname_en": "Rotterdam", "cityname_en": ""}, {"id": "NLDGM1719", "text": "Drimmelen", "tl2_name_en": "North Brabant", "tl3_name_en": "West-Noord-Brabant", "fuaname_en": "Breda", "cityname_en": ""}, {"id": "NLDGM1721", "text": "Bernheze", "tl2_name_en": "North Brabant", "tl3_name_en": "Noordoost-Noord-Brabant", "fuaname_en": "Oss", "cityname_en": ""}, {"id": "NLDGM1723", "text": "Alphen-Chaam", "tl2_name_en": "North Brabant", "tl3_name_en": "Midden-Noord-Brabant", "fuaname_en": "Breda", "cityname_en": ""}, {"id": "NLDGM1724", "text": "Bergeijk", "tl2_name_en": "North Brabant", "tl3_name_en": "Zuidoost-Noord-Brabant", "fuaname_en": "Eindhoven", "cityname_en": ""}, {"id": "NLDGM1728", "text": "Bladel", "tl2_name_en": "North Brabant", "tl3_name_en": "Zuidoost-Noord-Brabant", "fuaname_en": "Eindhoven", "cityname_en": ""}, {"id": "NLDGM1771", "text": "Geldrop-Mierlo", "tl2_name_en": "North Brabant", "tl3_name_en": "Zuidoost-Noord-Brabant", "fuaname_en": "Eindhoven", "cityname_en": ""}, {"id": "NLDGM1948", "text": "Meierijstad", "tl2_name_en": "North Brabant", "tl3_name_en": "Noordoost-Noord-Brabant", "fuaname_en": "", "cityname_en": ""}, {"id": "NLDGM1959", "text": "Altena", "tl2_name_en": "North Brabant", "tl3_name_en": "Midden-Noord-Brabant", "fuaname_en": "", "cityname_en": ""}, {"id": "NLDGM1982", "text": "Land van Cuijk", "tl2_name_en": "North Brabant", "tl3_name_en": "Noordoost-Noord-Brabant", "fuaname_en": "", "cityname_en": ""}, {"id": "NLDGM1991", "text": "Maashorst", "tl2_name_en": "North Brabant", "tl3_name_en": "Noordoost-Noord-Brabant", "fuaname_en": "", "cityname_en": ""}]}, {"tl2_id": "NL42", "tl2_name_en": "Limburg", "children": [{"id": "NLDGM0882", "text": "Landgraaf", "tl2_name_en": "Limburg", "tl3_name_en": "Zuid-Limburg", "fuaname_en": "Heerlen", "cityname_en": "Heerlen"}, {"id": "NLDGM0888", "text": "Beek", "tl2_name_en": "Limburg", "tl3_name_en": "Zuid-Limburg", "fuaname_en": "Sittard-Geleen", "cityname_en": ""}, {"id": "NLDGM0889", "text": "Beesel", "tl2_name_en": "Limburg", "tl3_name_en": "Noord-Limburg", "fuaname_en": "Venlo", "cityname_en": ""}, {"id": "NLDGM0893", "text": "Bergen (L.)", "tl2_name_en": "Limburg", "tl3_name_en": "Noord-Limburg", "fuaname_en": "", "cityname_en": ""}, {"id": "NLDGM0899", "text": "Brunssum", "tl2_name_en": "Limburg", "tl3_name_en": "Zuid-Limburg", "fuaname_en": "Heerlen", "cityname_en": "Heerlen"}, {"id": "NLDGM0907", "text": "Gennep", "tl2_name_en": "Limburg", "tl3_name_en": "Noord-Limburg", "fuaname_en": "", "cityname_en": ""}, {"id": "NLDGM0917", "text": "Heerlen", "tl2_name_en": "Limburg", "tl3_name_en": "Zuid-Limburg", "fuaname_en": "Heerlen", "cityname_en": "Heerlen"}, {"id": "NLDGM0928", "text": "Kerkrade", "tl2_name_en": "Limburg", "tl3_name_en": "Zuid-Limburg", "fuaname_en": "Heerlen", "cityname_en": "Heerlen"}, {"id": "NLDGM0935", "text": "Maastricht", "tl2_name_en": "Limburg", "tl3_name_en": "Zuid-Limburg", "fuaname_en": "Maastricht", "cityname_en": "Maastricht"}, {"id": "NLDGM0938", "text": "Meerssen", "tl2_name_en": "Limburg", "tl3_name_en": "Zuid-Limburg", "fuaname_en": "Maastricht", "cityname_en": ""}, {"id": "NLDGM0944", "text": "Mook en Middelaar", "tl2_name_en": "Limburg", "tl3_name_en": "Noord-Limburg", "fuaname_en": "Nijmegen", "cityname_en": ""}, {"id": "NLDGM0946", "text": "Nederweert", "tl2_name_en": "Limburg", "tl3_name_en": "Midden-Limburg", "fuaname_en": "", "cityname_en": ""}, {"id": "NLDGM0957", "text": "Roermond", "tl2_name_en": "Limburg", "tl3_name_en": "Midden-Limburg", "fuaname_en": "", "cityname_en": ""}, {"id": "NLDGM0965", "text": "Simpelveld", "tl2_name_en": "Limburg", "tl3_name_en": "Zuid-Limburg", "fuaname_en": "Heerlen", "cityname_en": ""}, {"id": "NLDGM0971", "text": "Stein", "tl2_name_en": "Limburg", "tl3_name_en": "Zuid-Limburg", "fuaname_en": "Sittard-Geleen", "cityname_en": "Sittard-Geleen"}, {"id": "NLDGM0981", "text": "Vaals", "tl2_name_en": "Limburg", "tl3_name_en": "Zuid-Limburg", "fuaname_en": "Heerlen", "cityname_en": ""}, {"id": "NLDGM0983", "text": "Venlo", "tl2_name_en": "Limburg", "tl3_name_en": "Noord-Limburg", "fuaname_en": "Venlo", "cityname_en": "Venlo"}, {"id": "NLDGM0984", "text": "Venray", "tl2_name_en": "Limburg", "tl3_name_en": "Noord-Limburg", "fuaname_en": "", "cityname_en": ""}, {"id": "NLDGM0986", "text": "Voerendaal", "tl2_name_en": "Limburg", "tl3_name_en": "Zuid-Limburg", "fuaname_en": "Heerlen", "cityname_en": ""}, {"id": "NLDGM0988", "text": "Weert", "tl2_name_en": "Limburg", "tl3_name_en": "Midden-Limburg", "fuaname_en": "", "cityname_en": ""}, {"id": "NLDGM0994", "text": "Valkenburg aan de Geul", "tl2_name_en": "Limburg", "tl3_name_en": "Zuid-Limburg", "fuaname_en": "Maastricht", "cityname_en": ""}, {"id": "NLDGM1507", "text": "Horst aan de Maas", "tl2_name_en": "Limburg", "tl3_name_en": "Noord-Limburg", "fuaname_en": "Venlo", "cityname_en": ""}, {"id": "NLDGM1640", "text": "Leudal", "tl2_name_en": "Limburg", "tl3_name_en": "Midden-Limburg", "fuaname_en": "", "cityname_en": ""}, {"id": "NLDGM1641", "text": "Maasgouw", "tl2_name_en": "Limburg", "tl3_name_en": "Midden-Limburg", "fuaname_en": "", "cityname_en": ""}, {"id": "NLDGM1669", "text": "Roerdalen", "tl2_name_en": "Limburg", "tl3_name_en": "Midden-Limburg", "fuaname_en": "", "cityname_en": ""}, {"id": "NLDGM1711", "text": "Echt-Susteren", "tl2_name_en": "Limburg", "tl3_name_en": "Midden-Limburg", "fuaname_en": "Sittard-Geleen", "cityname_en": ""}, {"id": "NLDGM1729", "text": "Gulpen-Wittem", "tl2_name_en": "Limburg", "tl3_name_en": "Zuid-Limburg", "fuaname_en": "Heerlen", "cityname_en": ""}, {"id": "NLDGM1883", "text": "Sittard-Geleen", "tl2_name_en": "Limburg", "tl3_name_en": "Zuid-Limburg", "fuaname_en": "Sittard-Geleen", "cityname_en": "Sittard-Geleen"}, {"id": "NLDGM1894", "text": "Peel en Maas", "tl2_name_en": "Limburg", "tl3_name_en": "Noord-Limburg", "fuaname_en": "Venlo", "cityname_en": ""}, {"id": "NLDGM1903", "text": "Eijsden-Margraten", "tl2_name_en": "Limburg", "tl3_name_en": "Zuid-Limburg", "fuaname_en": "Maastricht", "cityname_en": ""}, {"id": "NLDGM1954", "text": "Beekdaelen", "tl2_name_en": "Limburg", "tl3_name_en": "Zuid-Limburg", "fuaname_en": "", "cityname_en": ""}]}]