{
"type": "FeatureCollection",
"features": [
{ "type": "Feature", "properties": { "pk": "NZL194300", "iso3": "NZL", "table_name": "nzl_sau3_2022", "geo_level": "sau3", "launame": "Omanu Beach", "OLD_SH": 17.021276595744681, "WORKAGE_SH": 62.91793313069909, "YOUTH_SH": 19.756838905775076, "POP_CH": null, "POP_T": 3290.0, "pop_density_km2": 3210.3752613920537, "NETNAT_RATE": null, "BIRTHS_RATE": null, "DEATHS_RATE": null, "NETMIG_RATE": null, "NETMOB_RATE": null, "NETMOBMIG_RATE": null, "SEX_RATIO_TOT": 91.279069767441854, "MIGRANT_SH": null, "BUILT_S_NRES": 4.5725215052177344, "BUILT_S_RES": 203.0855106955415, "BUILT_S__T": 207.65803220075924, "BUILT_V_NRES": 34.804700728485287, "BUILT_V_RES": 1568.7750402087477, "BUILT_V__T": 1603.5797409372331, "BUILT_H": 7.6510832609953701, "BUILT_S_NRES_CH_2000_2020": 6.8078861736744729, "BUILT_S_RES_CH_2000_2020": 2.3576106424953638, "BUILT_S__T_CH_2000_2020": 2.4516066432718273, "BUILT_V_NRES_CH_2000_2020": 6.9300615968177768, "BUILT_V_RES_CH_2000_2020": 2.310247778741509, "BUILT_V__T_CH_2000_2020": 2.4062759310133219, "DEGURBA_L1": "City", "DEGURBA_L2": "City", "AIR_TEMP2M": 288.25765888429225, "AIR_TEMP2M_DIFF_1981_2010": 0.90408697501051161, "HOT_DAYS": 0.0, "HOT_DAYS_DIFF_1981_2010": 0.0, "ICING_DAYS": 0.0, "ICING_DAYS_DIFF_1981_2010": 0.0, "TROPICAL_NIGHTS": 1.6, "TROPICAL_NIGHTS_DIFF_1981_2010": 1.0000000000000004, "EXT_PRECIP_DAYS": 19.8, "EXT_PRECIP_DAYS_DIFF_1981_2010": 2.75, "PRECIP_SUM": 1446.8030430635044, "PRECIP_SUM_DIFF_1981_2010": 88.356434532001686, "SOIL_MOIST_L1_CH_1981_2018": -2.0968222178144869, "LST_DAY_SUMMER": 28.613769645272146, "LST_NIGHT_SUMMER": 15.183691474919021, "UHI_DAY_SUMMER": 2.2331661499825932, "UHI_NIGHT_SUMMER": 1.8932772761028118, "CDD_T_22C": 1.8853438059489747, "CDD_T_22C_DIFF_1981_2010": 1.5550709236993403, "HDD_T_15C": 532.00278499602859, "HDD_T_15C_DIFF_1981_2010": -166.82838128831574, "CDD_T_22C_DIFF_1981_2010_ref": 0.0, "HDD_T_15C_DIFF_1981_2010_ref": -1.3263464400855204e-14, "CDD_T_22C_CH": 1.5550709236993403, "HDD_T_15C_CH": -166.82838128831554, "UTCI_GT32": 2.6, "UTCI_GT32_DIFF_1981_2010": 2.0000000000000004, "UTCI_GT38": 0.0, "UTCI_GT38_DIFF_1981_2010": 0.0, "UTCI_GT46": 0.0, "UTCI_GT46_DIFF_1981_2010": 0.0, "FIRE_TOTAL_AREA_SH": null, "RIVER_FLOOD_RP100_POP_SH": 0.0, "COASTAL_FLOOD_RP100_POP_SH": null, "GREEN_AREA_CAPITA": 53.870825536896149, "GREEN_AREA_SHARE": 18.60968505938062, "year": 2020.0, "CROPLAND_AREA_KM2": 0.0, "FOREST_AREA_KM2": 0.0, "GRASS_AND_SHRUBLAND_AREA_KM2": 0.0, "OTHER_AREA_KM2": 0.0, "SETTLEMENT_AREA_KM2": 0.98684667373443113, "TOTAL_AREA_KM2": 1.024802315031909, "WETLANDS_AREA_KM2": 0.037955641297478117, "FOREST_CH": 0.0, "SOLAR_POWER_POT": 3.9368337212144895, "WIND_POWER_POT": 376.7087383243616, "ELEC_CONS": null, "GAS_CONS": null, "ENER_CONS": null, "NO2_POP_W_MEAN": 1.4158825691552883, "O3_POP_W_MEAN": 44.217049272420283, "PM10_POP_W_MEAN": 9.2226617911709283, "PM2_5_POP_W_MEAN": 5.4695090535615831, "PASG_VEH_CAP": null, "SH_ELEC_HYB_PASG_VEH": null, "SH_COMMUT_BIKE": 5.4054054054054053, "SH_COMMUT_CAR": 86.936936936936931, "SH_COMMUT_PUBLIC_TRANSPORT": 1.8018018018018018, "SH_COMMUT_WALK": 3.8288288288288288, "MAIN_COMMUT": "Car", "TP_TRANSIT_30_8000": 0.1845138374536649, "FIXED_AVG_D_DEV_NAT": -6.0797093892291274, "FIXED_AVG_U_DEV_NAT": 4.7868817835516673, "MOBILE_AVG_D_DEV_NAT": -39.031186867666641, "MOBILE_AVG_U_DEV_NAT": -57.681224880317444, "HOSPITALS_DIST_MEAN": 7341.8480531045543, "PHARMACIES_DIST_MEAN": null, "CHILDCARE_DIST_MEAN": 277.09802982093163, "HEI_DIST_MEAN": null, "SCHOOLS_DIST_MEAN": 304.88096334959698, "DISP_INC_EQ_MEAN": null, "DISP_INC_EQ_MEDIAN": null, "DISP_INC_EQ": null, "DISP_INC_EQ_GINI": null, "POV_RATE_60": null, "RENT_PRICE_T": null, "RENT_PRICE_T_M2": null, "SELL_PRICE_MEAN_T": null, "SELL_PRICE_MEAN_T_M2": null, "SELL_PRICE_MEDIAN_T": null, "SELL_PRICE_MEDIAN_T_M2": null, "SELL_PRICE_T": null, "SELL_PRICE_T_M2": null, "AVG_SURFACE": null, "NB_ROOMS": null, "MAIN_RES_SH": null, "NB_UNITS": null, "OCCUP_SH": null, "OWN_SH": null, "RENT_SH": null, "SECOND_RES_SH": null, "VAC_SH": null, "ENER_HEAT_SH_BIO": null, "ENER_HEAT_SH_COAL": null, "ENER_HEAT_SH_ELEC": null, "ENER_HEAT_SH_GAS": null, "ENER_HEAT_SH_OIL": null, "ENER_HEAT_SH_OTHER": null, "MAIN_ENER_HEAT": null, "UNEMP_RA": null, "EMP_RA": null, "E11_USD_PPP_PS": null, "E12_USD_PPP_PS": null, "E1_USD_PPP_PS": null, "MAIN_MUNIFI_EXPEND_x": null, "MAIN_MUNIFI_EXPEND_COMP": null, "MAIN_MUNIFI_EXPEND_y": null, "R11_USD_PPP_PS": null, "R1_USD_PPP_PS": null, "MAIN_MUNIFI_REVENUE": null, "D1_USD_PPP_PS": null, "fuacode": "NZL05F", "fuaname_en": "Tauranga", "citycode": "NZL05C", "cityname_en": "Tauranga", "tl2_id": "NZ14", "tl3_id": "NZ014", "tl2_name_en": "Bay of Plenty Region", "tl3_name_en": "Bay of Plenty Region", "POP_CH_2000_2020": null, "BUILT_S__T_POP_CH_DIFF_2000_2020": null, "BUILT_S_RES_POP_CH_DIFF_2000_2020": null, "BUILT_V__T_POP_CH_DIFF_2000_2020": null, "BUILT_V_RES_POP_CH_DIFF_2000_2020": null, "EXT_PRECIP_DAYS_1981_2010": null }, "geometry": { "type": "Polygon", "coordinates": [ [ [ 176.208688817534238, -37.653936483069558 ], [ 176.215754966990488, -37.65881068338669 ], [ 176.210824483392599, -37.662691666904351 ], [ 176.212451950740501, -37.664089883227689 ], [ 176.210702700654082, -37.667614032620683 ], [ 176.198934167209302, -37.654185666150404 ], [ 176.202732530211904, -37.652924468903521 ], [ 176.208688817534238, -37.653936483069558 ] ] ] } }
]
}
