{
"type": "FeatureCollection",
"features": [
{ "type": "Feature", "properties": { "pk": "NZL148200", "iso3": "NZL", "table_name": "nzl_sau3_2022", "geo_level": "sau3", "launame": "Favona North", "OLD_SH": 12.29235880398671, "WORKAGE_SH": 64.784053156146186, "YOUTH_SH": 23.588039867109636, "POP_CH": null, "POP_T": 3010.0, "pop_density_km2": 2708.8268716928983, "NETNAT_RATE": null, "BIRTHS_RATE": null, "DEATHS_RATE": null, "NETMIG_RATE": null, "NETMOB_RATE": null, "NETMOBMIG_RATE": null, "SEX_RATIO_TOT": 100.66666666666667, "MIGRANT_SH": null, "BUILT_S_NRES": 16.145598790636953, "BUILT_S_RES": 114.31956530092128, "BUILT_S__T": 130.46516409155822, "BUILT_V_NRES": 176.92888468507536, "BUILT_V_RES": 1059.6692787267377, "BUILT_V__T": 1236.5981634118132, "BUILT_H": 8.289647902885493, "BUILT_S_NRES_CH_2000_2020": 38.865220759101469, "BUILT_S_RES_CH_2000_2020": 16.772927404537825, "BUILT_S__T_CH_2000_2020": 19.118154263617239, "BUILT_V_NRES_CH_2000_2020": 44.19579507087051, "BUILT_V_RES_CH_2000_2020": 16.766705259675817, "BUILT_V__T_CH_2000_2020": 20.03357396373837, "DEGURBA_L1": "City", "DEGURBA_L2": "City", "AIR_TEMP2M": 288.98915041761859, "AIR_TEMP2M_DIFF_1981_2010": 0.82288297341987116, "HOT_DAYS": 0.0, "HOT_DAYS_DIFF_1981_2010": 0.0, "ICING_DAYS": 0.0, "ICING_DAYS_DIFF_1981_2010": 0.0, "TROPICAL_NIGHTS": 4.4, "TROPICAL_NIGHTS_DIFF_1981_2010": 1.7666666666666668, "EXT_PRECIP_DAYS": 11.8, "EXT_PRECIP_DAYS_DIFF_1981_2010": 1.3333333333333333, "PRECIP_SUM": 1164.1706615944934, "PRECIP_SUM_DIFF_1981_2010": 52.755541456734292, "SOIL_MOIST_L1_CH_1981_2018": -1.1292296009820291, "LST_DAY_SUMMER": 29.610815354687521, "LST_NIGHT_SUMMER": 15.358989401273286, "UHI_DAY_SUMMER": 1.7735459908136448, "UHI_NIGHT_SUMMER": 1.3201047986527328, "CDD_T_22C": 3.3180415089926214, "CDD_T_22C_DIFF_1981_2010": 2.1738365597195677, "HDD_T_15C": 392.63682813008273, "HDD_T_15C_DIFF_1981_2010": -132.73892732832093, "CDD_T_22C_DIFF_1981_2010_ref": 1.7763568394002506e-16, "HDD_T_15C_DIFF_1981_2010_ref": 3.6000831945178408e-14, "CDD_T_22C_CH": 2.1738365597195677, "HDD_T_15C_CH": -132.73892732832104, "UTCI_GT32": 1.6, "UTCI_GT32_DIFF_1981_2010": 1.3666666666666667, "UTCI_GT38": 0.0, "UTCI_GT38_DIFF_1981_2010": 0.0, "UTCI_GT46": 0.0, "UTCI_GT46_DIFF_1981_2010": 0.0, "FIRE_TOTAL_AREA_SH": null, "RIVER_FLOOD_RP100_POP_SH": 0.0, "COASTAL_FLOOD_RP100_POP_SH": null, "GREEN_AREA_CAPITA": 99.733932015549158, "GREEN_AREA_SHARE": 37.196986623580408, "year": 2020.0, "CROPLAND_AREA_KM2": 0.0, "FOREST_AREA_KM2": 0.0, "GRASS_AND_SHRUBLAND_AREA_KM2": 0.0, "OTHER_AREA_KM2": 0.0, "SETTLEMENT_AREA_KM2": 0.84180464027976509, "TOTAL_AREA_KM2": 1.1111821251692899, "WETLANDS_AREA_KM2": 0.26937748488952484, "FOREST_CH": 0.0, "SOLAR_POWER_POT": 3.7528567178640202, "WIND_POWER_POT": 256.06912695334165, "ELEC_CONS": null, "GAS_CONS": null, "ENER_CONS": null, "NO2_POP_W_MEAN": 6.2262561784591526, "O3_POP_W_MEAN": 41.447099965182133, "PM10_POP_W_MEAN": 12.449493483854896, "PM2_5_POP_W_MEAN": 7.3114830432568851, "PASG_VEH_CAP": null, "SH_ELEC_HYB_PASG_VEH": null, "SH_COMMUT_BIKE": 0.0, "SH_COMMUT_CAR": 88.075880758807585, "SH_COMMUT_PUBLIC_TRANSPORT": 8.1300813008130088, "SH_COMMUT_WALK": 3.2520325203252032, "MAIN_COMMUT": "Car", "TP_TRANSIT_30_8000": 0.114107618816467, "FIXED_AVG_D_DEV_NAT": 21.165354978685372, "FIXED_AVG_U_DEV_NAT": 27.254534959338713, "MOBILE_AVG_D_DEV_NAT": -94.993172007226036, "MOBILE_AVG_U_DEV_NAT": -86.464695408902188, "HOSPITALS_DIST_MEAN": 3120.1113597770691, "PHARMACIES_DIST_MEAN": null, "CHILDCARE_DIST_MEAN": 251.46354702390332, "HEI_DIST_MEAN": null, "SCHOOLS_DIST_MEAN": 580.38381443858941, "DISP_INC_EQ_MEAN": null, "DISP_INC_EQ_MEDIAN": null, "DISP_INC_EQ": null, "DISP_INC_EQ_GINI": null, "POV_RATE_60": null, "RENT_PRICE_T": null, "RENT_PRICE_T_M2": null, "SELL_PRICE_MEAN_T": null, "SELL_PRICE_MEAN_T_M2": null, "SELL_PRICE_MEDIAN_T": null, "SELL_PRICE_MEDIAN_T_M2": null, "SELL_PRICE_T": null, "SELL_PRICE_T_M2": null, "AVG_SURFACE": null, "NB_ROOMS": null, "MAIN_RES_SH": null, "NB_UNITS": null, "OCCUP_SH": null, "OWN_SH": null, "RENT_SH": null, "SECOND_RES_SH": null, "VAC_SH": null, "ENER_HEAT_SH_BIO": null, "ENER_HEAT_SH_COAL": null, "ENER_HEAT_SH_ELEC": null, "ENER_HEAT_SH_GAS": null, "ENER_HEAT_SH_OIL": null, "ENER_HEAT_SH_OTHER": null, "MAIN_ENER_HEAT": null, "UNEMP_RA": null, "EMP_RA": null, "E11_USD_PPP_PS": null, "E12_USD_PPP_PS": null, "E1_USD_PPP_PS": null, "MAIN_MUNIFI_EXPEND_x": null, "MAIN_MUNIFI_EXPEND_COMP": null, "MAIN_MUNIFI_EXPEND_y": null, "R11_USD_PPP_PS": null, "R1_USD_PPP_PS": null, "MAIN_MUNIFI_REVENUE": null, "D1_USD_PPP_PS": null, "fuacode": "NZL01F", "fuaname_en": "Auckland", "citycode": "NZL01C", "cityname_en": "Auckland", "tl2_id": "NZ12", "tl3_id": "NZ012", "tl2_name_en": "Auckland Region", "tl3_name_en": "Auckland Region", "POP_CH_2000_2020": null, "BUILT_S__T_POP_CH_DIFF_2000_2020": null, "BUILT_S_RES_POP_CH_DIFF_2000_2020": null, "BUILT_V__T_POP_CH_DIFF_2000_2020": null, "BUILT_V_RES_POP_CH_DIFF_2000_2020": null, "EXT_PRECIP_DAYS_1981_2010": null }, "geometry": { "type": "MultiPolygon", "coordinates": [ [ [ [ 174.809706399287563, -36.953339083937088 ], [ 174.803851867280116, -36.956275833002096 ], [ 174.800816316470531, -36.949000083653225 ], [ 174.810354283923999, -36.944264466606192 ], [ 174.817077350010408, -36.942976549808094 ], [ 174.815794449482581, -36.945635066711631 ], [ 174.816671633156346, -36.947114849817304 ], [ 174.814797333249004, -36.947441716849156 ], [ 174.816278466880561, -36.949180482844682 ], [ 174.814009633608379, -36.948571866143283 ], [ 174.814990950614344, -36.950639316679272 ], [ 174.812125233889844, -36.94973876662521 ], [ 174.813711800449084, -36.950884183352194 ], [ 174.809385017243073, -36.952136666770762 ], [ 174.809706399287563, -36.953339083937088 ] ] ], [ [ [ 174.820120550243644, -36.93926771689673 ], [ 174.819786850245322, -36.938882283433315 ], [ 174.820290166436649, -36.938614067164643 ], [ 174.820527633307591, -36.938852183222679 ], [ 174.820120550243644, -36.93926771689673 ] ] ], [ [ [ 174.813535099755086, -36.93878333293668 ], [ 174.813377266632699, -36.938599199822377 ], [ 174.81398541657407, -36.93804653320948 ], [ 174.813982900652832, -36.938413516687618 ], [ 174.813535099755086, -36.93878333293668 ] ] ] ] } }
]
}
