{
"type": "FeatureCollection",
"features": [
{ "type": "Feature", "properties": { "pk": "NZL237200", "iso3": "NZL", "table_name": "nzl_sau3_2022", "geo_level": "sau3", "launame": "Waikanae Park", "OLD_SH": 38.793103448275865, "WORKAGE_SH": 47.844827586206897, "YOUTH_SH": 13.793103448275861, "POP_CH": null, "POP_T": 2320.0, "pop_density_km2": 314.89966129344606, "NETNAT_RATE": null, "BIRTHS_RATE": null, "DEATHS_RATE": null, "NETMIG_RATE": null, "NETMOB_RATE": null, "NETMOBMIG_RATE": null, "SEX_RATIO_TOT": 82.677165354330711, "MIGRANT_SH": null, "BUILT_S_NRES": 1.0032394576733961, "BUILT_S_RES": 134.88550705388266, "BUILT_S__T": 135.88874651155604, "BUILT_V_NRES": 3.0249304951987082, "BUILT_V_RES": 519.59056937229263, "BUILT_V__T": 522.61549986749139, "BUILT_H": 3.1774228050595239, "BUILT_S_NRES_CH_2000_2020": 53.461314717859224, "BUILT_S_RES_CH_2000_2020": 31.991262085339805, "BUILT_S__T_CH_2000_2020": 32.127735890220499, "BUILT_V_NRES_CH_2000_2020": 47.05121094472176, "BUILT_V_RES_CH_2000_2020": 28.31856911008926, "BUILT_V__T_CH_2000_2020": 28.41325240972018, "DEGURBA_L1": "Town and semi-dense area", "DEGURBA_L2": "Suburban or peri-urban area", "AIR_TEMP2M": 285.51397237978375, "AIR_TEMP2M_DIFF_1981_2010": 0.90706812758558042, "HOT_DAYS": 0.0, "HOT_DAYS_DIFF_1981_2010": 0.0, "ICING_DAYS": 0.0, "ICING_DAYS_DIFF_1981_2010": 0.0, "TROPICAL_NIGHTS": 0.0, "TROPICAL_NIGHTS_DIFF_1981_2010": -0.03333333333333334, "EXT_PRECIP_DAYS": 22.2, "EXT_PRECIP_DAYS_DIFF_1981_2010": 5.9333333333333327, "PRECIP_SUM": 1736.6139918824265, "PRECIP_SUM_DIFF_1981_2010": 177.73636018534015, "SOIL_MOIST_L1_CH_1981_2018": 0.92445086355776862, "LST_DAY_SUMMER": 25.604273552100778, "LST_NIGHT_SUMMER": 11.902615416539831, "UHI_DAY_SUMMER": null, "UHI_NIGHT_SUMMER": null, "CDD_T_22C": 0.0, "CDD_T_22C_DIFF_1981_2010": -0.011474003261990141, "HDD_T_15C": 1107.2720862070657, "HDD_T_15C_DIFF_1981_2010": -273.64256762186716, "CDD_T_22C_DIFF_1981_2010_ref": 1.8503717077085942e-18, "HDD_T_15C_DIFF_1981_2010_ref": 9.0949470177292829e-14, "CDD_T_22C_CH": -0.011474003261990141, "HDD_T_15C_CH": -273.6425676218671, "UTCI_GT32": 0.0, "UTCI_GT32_DIFF_1981_2010": 0.0, "UTCI_GT38": 0.0, "UTCI_GT38_DIFF_1981_2010": 0.0, "UTCI_GT46": 0.0, "UTCI_GT46_DIFF_1981_2010": 0.0, "FIRE_TOTAL_AREA_SH": null, "RIVER_FLOOD_RP100_POP_SH": 0.0, "COASTAL_FLOOD_RP100_POP_SH": null, "GREEN_AREA_CAPITA": 2475.0875866516876, "GREEN_AREA_SHARE": 86.799688875359195, "year": 2020.0, "CROPLAND_AREA_KM2": 0.31574683510358303, "FOREST_AREA_KM2": 0.15787341755179152, "GRASS_AND_SHRUBLAND_AREA_KM2": 5.367696196760912, "OTHER_AREA_KM2": 0.0, "SETTLEMENT_AREA_KM2": 1.5261097030006514, "TOTAL_AREA_KM2": 7.3674261524169378, "WETLANDS_AREA_KM2": 0.0, "FOREST_CH": 0.0, "SOLAR_POWER_POT": 3.6142286249938329, "WIND_POWER_POT": 488.03332605766406, "ELEC_CONS": null, "GAS_CONS": null, "ENER_CONS": null, "NO2_POP_W_MEAN": 1.0201013366777261, "O3_POP_W_MEAN": 43.539752580225468, "PM10_POP_W_MEAN": 10.78950782227912, "PM2_5_POP_W_MEAN": 6.1512336216692347, "PASG_VEH_CAP": null, "SH_ELEC_HYB_PASG_VEH": null, "SH_COMMUT_BIKE": 2.5423728813559321, "SH_COMMUT_CAR": 80.932203389830505, "SH_COMMUT_PUBLIC_TRANSPORT": 13.559322033898304, "SH_COMMUT_WALK": 1.271186440677966, "MAIN_COMMUT": "Car", "TP_TRANSIT_30_8000": 0.19964245086608601, "FIXED_AVG_D_DEV_NAT": 45.517678879530692, "FIXED_AVG_U_DEV_NAT": -3.8706819117813831, "MOBILE_AVG_D_DEV_NAT": -28.486721122576849, "MOBILE_AVG_U_DEV_NAT": -16.499740625720339, "HOSPITALS_DIST_MEAN": 33866.312928690699, "PHARMACIES_DIST_MEAN": null, "CHILDCARE_DIST_MEAN": 923.85244237517043, "HEI_DIST_MEAN": null, "SCHOOLS_DIST_MEAN": 1349.5739687747057, "DISP_INC_EQ_MEAN": null, "DISP_INC_EQ_MEDIAN": null, "DISP_INC_EQ": null, "DISP_INC_EQ_GINI": null, "POV_RATE_60": null, "RENT_PRICE_T": null, "RENT_PRICE_T_M2": null, "SELL_PRICE_MEAN_T": null, "SELL_PRICE_MEAN_T_M2": null, "SELL_PRICE_MEDIAN_T": null, "SELL_PRICE_MEDIAN_T_M2": null, "SELL_PRICE_T": null, "SELL_PRICE_T_M2": null, "AVG_SURFACE": null, "NB_ROOMS": null, "MAIN_RES_SH": null, "NB_UNITS": null, "OCCUP_SH": null, "OWN_SH": null, "RENT_SH": null, "SECOND_RES_SH": null, "VAC_SH": null, "ENER_HEAT_SH_BIO": null, "ENER_HEAT_SH_COAL": null, "ENER_HEAT_SH_ELEC": null, "ENER_HEAT_SH_GAS": null, "ENER_HEAT_SH_OIL": null, "ENER_HEAT_SH_OTHER": null, "MAIN_ENER_HEAT": null, "UNEMP_RA": null, "EMP_RA": null, "E11_USD_PPP_PS": null, "E12_USD_PPP_PS": null, "E1_USD_PPP_PS": null, "MAIN_MUNIFI_EXPEND_x": null, "MAIN_MUNIFI_EXPEND_COMP": null, "MAIN_MUNIFI_EXPEND_y": null, "R11_USD_PPP_PS": null, "R1_USD_PPP_PS": null, "MAIN_MUNIFI_REVENUE": null, "D1_USD_PPP_PS": null, "fuacode": "NZL16F", "fuaname_en": "Kapiti Coast", "citycode": "NZL16C", "cityname_en": "Kapiti Coast", "tl2_id": "NZ19", "tl3_id": "NZ019", "tl2_name_en": "Wellington Region", "tl3_name_en": "Wellington Region", "POP_CH_2000_2020": null, "BUILT_S__T_POP_CH_DIFF_2000_2020": null, "BUILT_S_RES_POP_CH_DIFF_2000_2020": null, "BUILT_V__T_POP_CH_DIFF_2000_2020": null, "BUILT_V_RES_POP_CH_DIFF_2000_2020": null, "EXT_PRECIP_DAYS_1981_2010": null }, "geometry": { "type": "Polygon", "coordinates": [ [ [ 175.071460899453911, -40.849575066288729 ], [ 175.054615749419895, -40.871072366707907 ], [ 175.052124417408265, -40.871620266631005 ], [ 175.051842566463961, -40.879255449526887 ], [ 175.050487317200265, -40.879179483514875 ], [ 175.050030255231377, -40.882055542186457 ], [ 175.040965500615471, -40.88162654180428 ], [ 175.039187883860421, -40.876510799769477 ], [ 175.035407916807571, -40.877168999607555 ], [ 175.032622349959382, -40.875635832973167 ], [ 175.029849949819607, -40.877038999866841 ], [ 175.029827458729415, -40.873918978744996 ], [ 175.026692183356914, -40.871868432910688 ], [ 175.029880983549219, -40.872664083583778 ], [ 175.029483366855033, -40.869542600256615 ], [ 175.033534617059274, -40.867725266770321 ], [ 175.031863350573616, -40.86675144976477 ], [ 175.039349533390407, -40.864183332637154 ], [ 175.037022017206567, -40.857548766112771 ], [ 175.046356099661068, -40.849108300402904 ], [ 175.047653116336647, -40.849813366296942 ], [ 175.049185582721009, -40.846351033013548 ], [ 175.051753966251567, -40.843656700165631 ], [ 175.071460899453911, -40.849575066288729 ] ] ] } }
]
}
