{
"type": "FeatureCollection",
"features": [
{ "type": "Feature", "properties": { "pk": "NZL333800", "iso3": "NZL", "table_name": "nzl_sau3_2022", "geo_level": "sau3", "launame": "Glenroy-Hororata", "OLD_SH": 13.703703703703704, "WORKAGE_SH": 64.81481481481481, "YOUTH_SH": 21.111111111111111, "POP_CH": null, "POP_T": 1350.0, "pop_density_km2": 2.0935126336203034, "NETNAT_RATE": null, "BIRTHS_RATE": null, "DEATHS_RATE": null, "NETMIG_RATE": null, "NETMOB_RATE": null, "NETMOBMIG_RATE": null, "SEX_RATIO_TOT": 117.74193548387096, "MIGRANT_SH": null, "BUILT_S_NRES": 9.0202175345977231, "BUILT_S_RES": 521.58044299234712, "BUILT_S__T": 530.60066052694492, "BUILT_V_NRES": 22.559687014002289, "BUILT_V_RES": 1304.3650727245913, "BUILT_V__T": 1326.9247597385936, "BUILT_H": 2.5, "BUILT_S_NRES_CH_2000_2020": 49.727862675319237, "BUILT_S_RES_CH_2000_2020": 74.109210160729461, "BUILT_S__T_CH_2000_2020": 73.628564000346657, "BUILT_V_NRES_CH_2000_2020": 49.738417109613692, "BUILT_V_RES_CH_2000_2020": 74.092514650299066, "BUILT_V__T_CH_2000_2020": 73.612442599336362, "DEGURBA_L1": "Rural area", "DEGURBA_L2": "Mostly uninhabited area", "AIR_TEMP2M": 283.50626967115528, "AIR_TEMP2M_DIFF_1981_2010": 1.013372604278618, "HOT_DAYS": 0.0, "HOT_DAYS_DIFF_1981_2010": 0.0, "ICING_DAYS": 0.271193695425612, "ICING_DAYS_DIFF_1981_2010": -0.94707455204875335, "TROPICAL_NIGHTS": 0.66982979586025682, "TROPICAL_NIGHTS_DIFF_1981_2010": 0.55429820169977551, "EXT_PRECIP_DAYS": 9.0864283802937535, "EXT_PRECIP_DAYS_DIFF_1981_2010": -0.40787639698096623, "PRECIP_SUM": 1117.6781032365138, "PRECIP_SUM_DIFF_1981_2010": 37.262048398340447, "SOIL_MOIST_L1_CH_1981_2018": -0.42608039419635979, "LST_DAY_SUMMER": 24.611102996901032, "LST_NIGHT_SUMMER": 10.306282613444184, "UHI_DAY_SUMMER": null, "UHI_NIGHT_SUMMER": null, "CDD_T_22C": 2.9636552203444104, "CDD_T_22C_DIFF_1981_2010": 1.9907088392036723, "HDD_T_15C": 1876.856859262273, "HDD_T_15C_DIFF_1981_2010": -320.80361931354497, "CDD_T_22C_DIFF_1981_2010_ref": -1.1842378929335003e-16, "HDD_T_15C_DIFF_1981_2010_ref": 1.2126596023639043e-13, "CDD_T_22C_CH": 1.990708839203672, "HDD_T_15C_CH": -320.80361931354469, "UTCI_GT32": 1.5087719298245612, "UTCI_GT32_DIFF_1981_2010": 1.3161493477282948, "UTCI_GT38": 0.0, "UTCI_GT38_DIFF_1981_2010": 0.0, "UTCI_GT46": 0.0, "UTCI_GT46_DIFF_1981_2010": 0.0, "FIRE_TOTAL_AREA_SH": null, "RIVER_FLOOD_RP100_POP_SH": 0.0, "COASTAL_FLOOD_RP100_POP_SH": null, "GREEN_AREA_CAPITA": 335468.81972556317, "GREEN_AREA_SHARE": 82.488639390559442, "year": 2020.0, "CROPLAND_AREA_KM2": 25.256161342103955, "FOREST_AREA_KM2": 70.122989138076875, "GRASS_AND_SHRUBLAND_AREA_KM2": 527.48235791258878, "OTHER_AREA_KM2": 21.542019968265137, "SETTLEMENT_AREA_KM2": 0.37141413738388168, "TOTAL_AREA_KM2": 644.84922532589542, "WETLANDS_AREA_KM2": 0.074282827476776336, "FOREST_CH": -4.1624365482233436, "SOLAR_POWER_POT": 3.8173658818292289, "WIND_POWER_POT": 1657.4166654996084, "ELEC_CONS": null, "GAS_CONS": null, "ENER_CONS": null, "NO2_POP_W_MEAN": 1.4613295502924095, "O3_POP_W_MEAN": 36.930482623650903, "PM10_POP_W_MEAN": 4.3478588010843939, "PM2_5_POP_W_MEAN": 2.8543756710138601, "PASG_VEH_CAP": null, "SH_ELEC_HYB_PASG_VEH": null, "SH_COMMUT_BIKE": 0.64935064935064934, "SH_COMMUT_CAR": 85.064935064935071, "SH_COMMUT_PUBLIC_TRANSPORT": 0.0, "SH_COMMUT_WALK": 5.8441558441558445, "MAIN_COMMUT": "Car", "TP_TRANSIT_30_8000": null, "FIXED_AVG_D_DEV_NAT": -71.971040335652077, "FIXED_AVG_U_DEV_NAT": -81.642871041645023, "MOBILE_AVG_D_DEV_NAT": -23.182211482071402, "MOBILE_AVG_U_DEV_NAT": -2.8003057837032692, "HOSPITALS_DIST_MEAN": 19578.104292403499, "PHARMACIES_DIST_MEAN": null, "CHILDCARE_DIST_MEAN": 6775.0175309136739, "HEI_DIST_MEAN": null, "SCHOOLS_DIST_MEAN": 4340.058975049029, "DISP_INC_EQ_MEAN": null, "DISP_INC_EQ_MEDIAN": null, "DISP_INC_EQ": null, "DISP_INC_EQ_GINI": null, "POV_RATE_60": null, "RENT_PRICE_T": null, "RENT_PRICE_T_M2": null, "SELL_PRICE_MEAN_T": null, "SELL_PRICE_MEAN_T_M2": null, "SELL_PRICE_MEDIAN_T": null, "SELL_PRICE_MEDIAN_T_M2": null, "SELL_PRICE_T": null, "SELL_PRICE_T_M2": null, "AVG_SURFACE": null, "NB_ROOMS": null, "MAIN_RES_SH": null, "NB_UNITS": null, "OCCUP_SH": null, "OWN_SH": null, "RENT_SH": null, "SECOND_RES_SH": null, "VAC_SH": null, "ENER_HEAT_SH_BIO": null, "ENER_HEAT_SH_COAL": null, "ENER_HEAT_SH_ELEC": null, "ENER_HEAT_SH_GAS": null, "ENER_HEAT_SH_OIL": null, "ENER_HEAT_SH_OTHER": null, "MAIN_ENER_HEAT": null, "UNEMP_RA": null, "EMP_RA": null, "E11_USD_PPP_PS": null, "E12_USD_PPP_PS": null, "E1_USD_PPP_PS": null, "MAIN_MUNIFI_EXPEND_x": null, "MAIN_MUNIFI_EXPEND_COMP": null, "MAIN_MUNIFI_EXPEND_y": null, "R11_USD_PPP_PS": null, "R1_USD_PPP_PS": null, "MAIN_MUNIFI_REVENUE": null, "D1_USD_PPP_PS": null, "fuacode": null, "fuaname_en": null, "citycode": null, "cityname_en": null, "tl2_id": "NZ23", "tl3_id": "NZ023", "tl2_name_en": "Canterbury Region", "tl3_name_en": "Canterbury Region", "POP_CH_2000_2020": null, "BUILT_S__T_POP_CH_DIFF_2000_2020": null, "BUILT_S_RES_POP_CH_DIFF_2000_2020": null, "BUILT_V__T_POP_CH_DIFF_2000_2020": null, "BUILT_V_RES_POP_CH_DIFF_2000_2020": null, "EXT_PRECIP_DAYS_1981_2010": null }, "geometry": { "type": "Polygon", "coordinates": [ [ [ 171.691463216412529, -43.315373450016445 ], [ 171.816666133378476, -43.415986167178673 ], [ 171.825238316597449, -43.41557138320772 ], [ 171.826241949730871, -43.412545299888784 ], [ 171.830356849834942, -43.410886882943316 ], [ 171.832069667318791, -43.405558566186038 ], [ 171.835105583428657, -43.407544166424309 ], [ 171.837038749347045, -43.405621066388179 ], [ 171.838158700020472, -43.407990299449274 ], [ 171.843741083399777, -43.406501666242079 ], [ 171.848626799084826, -43.408050316527486 ], [ 171.852229266830221, -43.40542836651619 ], [ 171.856955616898915, -43.406951049618016 ], [ 171.863007983603808, -43.405171883480477 ], [ 171.864855450506866, -43.408415866442986 ], [ 171.860151183879225, -43.413218099902451 ], [ 171.860220966817678, -43.415191299421608 ], [ 171.867668649071419, -43.419180916916005 ], [ 171.872930849984186, -43.417899716168861 ], [ 171.875373016966904, -43.418894899661638 ], [ 171.870703966011547, -43.424231883160239 ], [ 171.874011482750433, -43.426164299540439 ], [ 171.880142283555415, -43.426528533224456 ], [ 171.879445516597627, -43.431307966305916 ], [ 171.883153416737002, -43.434827283448726 ], [ 171.891538933398721, -43.432957516929335 ], [ 171.895729983388918, -43.439031699749115 ], [ 171.897448217502301, -43.445593116327807 ], [ 171.894865917134979, -43.453083333069245 ], [ 171.897161816351201, -43.456468183214085 ], [ 171.892748316445648, -43.45833406668347 ], [ 171.891801833907692, -43.460239683180347 ], [ 171.896816416827704, -43.467149033321547 ], [ 171.895595567427677, -43.472961533880472 ], [ 171.901863900792591, -43.474840349536308 ], [ 171.907553266545591, -43.478699466268047 ], [ 171.915297232590262, -43.478802050014757 ], [ 171.921313750482312, -43.481221867021112 ], [ 171.924891967005209, -43.480562000030204 ], [ 171.932936132699268, -43.486468516565736 ], [ 171.952037183061492, -43.485131833082065 ], [ 171.959914350078151, -43.486747999934572 ], [ 171.96413174973631, -43.491328866125897 ], [ 171.986394266440755, -43.505153199579553 ], [ 171.997058867063856, -43.520178516768176 ], [ 172.004554567333543, -43.523417132851122 ], [ 172.015998632737677, -43.545619416854422 ], [ 172.028236567324626, -43.551532150042519 ], [ 172.037449849890919, -43.560185683448793 ], [ 172.041671449842511, -43.572359532952881 ], [ 172.046877984058483, -43.575709866489035 ], [ 172.033116717627905, -43.583642366843506 ], [ 172.036270717338567, -43.585333133279619 ], [ 172.028032167288956, -43.603056916371663 ], [ 171.996574600724585, -43.577616116670413 ], [ 171.978800233760552, -43.593866799848826 ], [ 171.978578867197882, -43.60805863318096 ], [ 171.911064733024887, -43.583283550114537 ], [ 171.893355833302678, -43.634394533461261 ], [ 171.85000186733194, -43.602259649615782 ], [ 171.829285849841852, -43.617180700169378 ], [ 171.815883415872435, -43.624842817233407 ], [ 171.793354383484285, -43.604520666317079 ], [ 171.739530832837886, -43.565716749393395 ], [ 171.714313633056918, -43.543499833090998 ], [ 171.708519566126881, -43.541475616303444 ], [ 171.690969749177526, -43.543033716853266 ], [ 171.68529833399927, -43.542183249841507 ], [ 171.663606334152519, -43.529615583042713 ], [ 171.659766867255797, -43.526063266922435 ], [ 171.655558433018854, -43.517436783494091 ], [ 171.640254399815802, -43.513454049939988 ], [ 171.643199250746903, -43.508051766199017 ], [ 171.63164793365118, -43.504593049896577 ], [ 171.632214882491098, -43.499806816483584 ], [ 171.624426850660029, -43.494817799957602 ], [ 171.62514373246205, -43.491969399402663 ], [ 171.622110066921891, -43.488564799777173 ], [ 171.621953699816061, -43.483840116209528 ], [ 171.606858033102867, -43.479457866459576 ], [ 171.60867891610701, -43.476304366676636 ], [ 171.622151900146179, -43.470619582776294 ], [ 171.624333700269545, -43.466674550226585 ], [ 171.619965883212274, -43.459979750194499 ], [ 171.611461399233008, -43.45300110021622 ], [ 171.600135883019078, -43.435857066434565 ], [ 171.593225817564445, -43.430717333456379 ], [ 171.586025449520776, -43.426390799970982 ], [ 171.582744832738769, -43.415144399950982 ], [ 171.574070316220485, -43.409727416919253 ], [ 171.567807666569507, -43.399693999758483 ], [ 171.576584016872374, -43.397719466877746 ], [ 171.584727783265265, -43.398556949647656 ], [ 171.593314149598882, -43.391732067043485 ], [ 171.583550817032233, -43.378819900064769 ], [ 171.594970699972208, -43.370376183500021 ], [ 171.59069820050118, -43.360639632676303 ], [ 171.591483778470973, -43.35573258780272 ], [ 171.589520012359003, -43.347060226651671 ], [ 171.605523735451015, -43.340958351048272 ], [ 171.615028790172772, -43.340964273006932 ], [ 171.618903992968853, -43.344246463688656 ], [ 171.620877250147913, -43.342445346567388 ], [ 171.627283145252363, -43.343827988301797 ], [ 171.633585606619135, -43.339939125558516 ], [ 171.640585359624851, -43.34133288199358 ], [ 171.655843952110644, -43.334220661958483 ], [ 171.659758655582323, -43.335417318748227 ], [ 171.666605982390934, -43.332370432754075 ], [ 171.671254171719539, -43.332263721173675 ], [ 171.674761831762339, -43.328998808744274 ], [ 171.676271728186805, -43.331153332535948 ], [ 171.681720336617417, -43.325948726442526 ], [ 171.687520471135201, -43.323242294095742 ], [ 171.691463216412529, -43.315373450016445 ] ] ] } }
]
}
