{
"type": "FeatureCollection",
"features": [
{ "type": "Feature", "properties": { "pk": "NZL324600", "iso3": "NZL", "table_name": "nzl_sau3_2022", "geo_level": "sau3", "launame": "Shirley East", "OLD_SH": 22.727272727272727, "WORKAGE_SH": 63.257575757575758, "YOUTH_SH": 14.772727272727273, "POP_CH": null, "POP_T": 2640.0, "pop_density_km2": 1554.4214149417667, "NETNAT_RATE": null, "BIRTHS_RATE": null, "DEATHS_RATE": null, "NETMIG_RATE": null, "NETMOB_RATE": null, "NETMOBMIG_RATE": null, "SEX_RATIO_TOT": 94.117647058823536, "MIGRANT_SH": null, "BUILT_S_NRES": 10.11550489657421, "BUILT_S_RES": 103.62427226282419, "BUILT_S__T": 113.7397771593984, "BUILT_V_NRES": 96.869215590711704, "BUILT_V_RES": 645.44671022120667, "BUILT_V__T": 742.31592581191842, "BUILT_H": 5.5324404818340414, "BUILT_S_NRES_CH_2000_2020": 4.7269656100715247, "BUILT_S_RES_CH_2000_2020": 16.906431369391033, "BUILT_S__T_CH_2000_2020": 15.709650899528258, "BUILT_V_NRES_CH_2000_2020": 4.5341755019174377, "BUILT_V_RES_CH_2000_2020": 9.728665238224016, "BUILT_V__T_CH_2000_2020": 9.0217056782809184, "DEGURBA_L1": "City", "DEGURBA_L2": "City", "AIR_TEMP2M": 285.55294429875767, "AIR_TEMP2M_DIFF_1981_2010": 1.0781060862766707, "HOT_DAYS": 0.0, "HOT_DAYS_DIFF_1981_2010": 0.0, "ICING_DAYS": 0.0, "ICING_DAYS_DIFF_1981_2010": 0.0, "TROPICAL_NIGHTS": 1.2, "TROPICAL_NIGHTS_DIFF_1981_2010": 0.94995917837393173, "EXT_PRECIP_DAYS": 4.4001632865042728, "EXT_PRECIP_DAYS_DIFF_1981_2010": 1.2832925117072649, "PRECIP_SUM": 640.79838608383807, "PRECIP_SUM_DIFF_1981_2010": 6.7490788397796351, "SOIL_MOIST_L1_CH_1981_2018": -1.8860781539897342, "LST_DAY_SUMMER": 30.376862405772187, "LST_NIGHT_SUMMER": 12.922815319656175, "UHI_DAY_SUMMER": 3.1913779484515148, "UHI_NIGHT_SUMMER": 1.6988260852939263, "CDD_T_22C": 6.1850739050043542, "CDD_T_22C_DIFF_1981_2010": 4.8803238899300734, "HDD_T_15C": 1233.3323883115052, "HDD_T_15C_DIFF_1981_2010": -313.46924615122009, "CDD_T_22C_DIFF_1981_2010_ref": 1.7763568394002506e-16, "HDD_T_15C_DIFF_1981_2010_ref": 9.0949470177292829e-14, "CDD_T_22C_CH": 4.8803238899300734, "HDD_T_15C_CH": -313.4692461512202, "UTCI_GT32": 0.2, "UTCI_GT32_DIFF_1981_2010": 0.2, "UTCI_GT38": 0.0, "UTCI_GT38_DIFF_1981_2010": 0.0, "UTCI_GT46": 0.0, "UTCI_GT46_DIFF_1981_2010": 0.0, "FIRE_TOTAL_AREA_SH": null, "RIVER_FLOOD_RP100_POP_SH": 0.0, "COASTAL_FLOOD_RP100_POP_SH": null, "GREEN_AREA_CAPITA": 208.06686418065678, "GREEN_AREA_SHARE": 47.761402720955495, "year": 2020.0, "CROPLAND_AREA_KM2": 0.0, "FOREST_AREA_KM2": 0.0, "GRASS_AND_SHRUBLAND_AREA_KM2": 0.48525175157472406, "OTHER_AREA_KM2": 0.0, "SETTLEMENT_AREA_KM2": 1.2131293789368103, "TOTAL_AREA_KM2": 1.6983811305115344, "WETLANDS_AREA_KM2": 0.0, "FOREST_CH": 0.0, "SOLAR_POWER_POT": 3.8032862832469418, "WIND_POWER_POT": 233.18884611328579, "ELEC_CONS": null, "GAS_CONS": null, "ENER_CONS": null, "NO2_POP_W_MEAN": 3.6337484383830652, "O3_POP_W_MEAN": 35.501377596592363, "PM10_POP_W_MEAN": 6.7370344524771628, "PM2_5_POP_W_MEAN": 4.3122107333779791, "PASG_VEH_CAP": null, "SH_ELEC_HYB_PASG_VEH": null, "SH_COMMUT_BIKE": 4.2183622828784122, "SH_COMMUT_CAR": 88.58560794044665, "SH_COMMUT_PUBLIC_TRANSPORT": 3.225806451612903, "SH_COMMUT_WALK": 2.4813895781637716, "MAIN_COMMUT": "Car", "TP_TRANSIT_30_8000": 0.15924222223049919, "FIXED_AVG_D_DEV_NAT": 35.775141868159054, "FIXED_AVG_U_DEV_NAT": 41.880438294922229, "MOBILE_AVG_D_DEV_NAT": 32.188225272764164, "MOBILE_AVG_U_DEV_NAT": 19.16633039790154, "HOSPITALS_DIST_MEAN": 1988.833874304604, "PHARMACIES_DIST_MEAN": null, "CHILDCARE_DIST_MEAN": 834.31444870103689, "HEI_DIST_MEAN": null, "SCHOOLS_DIST_MEAN": 1122.8719740471352, "DISP_INC_EQ_MEAN": null, "DISP_INC_EQ_MEDIAN": null, "DISP_INC_EQ": null, "DISP_INC_EQ_GINI": null, "POV_RATE_60": null, "RENT_PRICE_T": null, "RENT_PRICE_T_M2": null, "SELL_PRICE_MEAN_T": null, "SELL_PRICE_MEAN_T_M2": null, "SELL_PRICE_MEDIAN_T": null, "SELL_PRICE_MEDIAN_T_M2": null, "SELL_PRICE_T": null, "SELL_PRICE_T_M2": null, "AVG_SURFACE": null, "NB_ROOMS": null, "MAIN_RES_SH": null, "NB_UNITS": null, "OCCUP_SH": null, "OWN_SH": null, "RENT_SH": null, "SECOND_RES_SH": null, "VAC_SH": null, "ENER_HEAT_SH_BIO": null, "ENER_HEAT_SH_COAL": null, "ENER_HEAT_SH_ELEC": null, "ENER_HEAT_SH_GAS": null, "ENER_HEAT_SH_OIL": null, "ENER_HEAT_SH_OTHER": null, "MAIN_ENER_HEAT": null, "UNEMP_RA": null, "EMP_RA": null, "E11_USD_PPP_PS": null, "E12_USD_PPP_PS": null, "E1_USD_PPP_PS": null, "MAIN_MUNIFI_EXPEND_x": null, "MAIN_MUNIFI_EXPEND_COMP": null, "MAIN_MUNIFI_EXPEND_y": null, "R11_USD_PPP_PS": null, "R1_USD_PPP_PS": null, "MAIN_MUNIFI_REVENUE": null, "D1_USD_PPP_PS": null, "fuacode": "NZL02F", "fuaname_en": "Christchurch", "citycode": "NZL02C", "cityname_en": "Christchurch", "tl2_id": "NZ23", "tl3_id": "NZ023", "tl2_name_en": "Canterbury Region", "tl3_name_en": "Canterbury Region", "POP_CH_2000_2020": null, "BUILT_S__T_POP_CH_DIFF_2000_2020": null, "BUILT_S_RES_POP_CH_DIFF_2000_2020": null, "BUILT_V__T_POP_CH_DIFF_2000_2020": null, "BUILT_V_RES_POP_CH_DIFF_2000_2020": null, "EXT_PRECIP_DAYS_1981_2010": null }, "geometry": { "type": "Polygon", "coordinates": [ [ [ 172.67413048546527, -43.507312816948115 ], [ 172.662870399994546, -43.508044750026187 ], [ 172.660970150202104, -43.489693583282431 ], [ 172.673177567217436, -43.489989499695199 ], [ 172.674039566235621, -43.494360350194263 ], [ 172.67168711606007, -43.495153750094367 ], [ 172.670274865881197, -43.500190183324435 ], [ 172.671804082486915, -43.502989782822659 ], [ 172.674872533250408, -43.504222233472206 ], [ 172.67413048546527, -43.507312816948115 ] ] ] } }
]
}
